{
    "schema":{
        "fields":[
            {
                "name":"index",
                "type":"integer"
            },
            {
                "name":"sort",
                "type":"string"
            },
            {
                "name":"name",
                "type":"string"
            },
            {
                "name":"search_code",
                "type":"string"
            },
            {
                "name":"apt_type",
                "type":"string"
            },
            {
                "name":"apt_year",
                "type":"number"
            },
            {
                "name":"value_score",
                "type":"number"
            },
            {
                "name":"region",
                "type":"string"
            },
            {
                "name":"region_code",
                "type":"string"
            },
            {
                "name":"sub_region_code",
                "type":"string"
            },
            {
                "name":"shorten_url",
                "type":"string"
            }
        ],
        "primaryKey":[
            "index"
        ],
        "pandas_version":"1.4.0"
    },
    "data":[
        {
            "index":0,
            "sort":"balanced",
            "name":"디큐브시티(주상복합)",
            "search_code":"27310",
            "apt_type":"아파트",
            "apt_year":11.0,
            "value_score":73.7371,
            "region":"서울시 구로구",
            "region_code":"Seoul",
            "sub_region_code":"1153000000_Seoul_Guro",
            "shorten_url":"https:\/\/me2.do\/55yYvTpq"
        },
        {
            "index":1,
            "sort":"balanced",
            "name":"신도림태영타운",
            "search_code":"3204",
            "apt_type":"아파트",
            "apt_year":22.0,
            "value_score":69.8371,
            "region":"서울시 구로구",
            "region_code":"Seoul",
            "sub_region_code":"1153000000_Seoul_Guro",
            "shorten_url":"https:\/\/me2.do\/55yYvTpq"
        },
        {
            "index":2,
            "sort":"balanced",
            "name":"신도림대림1,2차(e편한세상)",
            "search_code":"3354",
            "apt_type":"아파트",
            "apt_year":23.0,
            "value_score":66.6371,
            "region":"서울시 구로구",
            "region_code":"Seoul",
            "sub_region_code":"1153000000_Seoul_Guro",
            "shorten_url":"https:\/\/me2.do\/55yYvTpq"
        },
        {
            "index":3,
            "sort":"balanced",
            "name":"신도림동아3차",
            "search_code":"3210",
            "apt_type":"아파트",
            "apt_year":22.0,
            "value_score":66.3871,
            "region":"서울시 구로구",
            "region_code":"Seoul",
            "sub_region_code":"1153000000_Seoul_Guro",
            "shorten_url":"https:\/\/me2.do\/55yYvTpq"
        },
        {
            "index":4,
            "sort":"balanced",
            "name":"신도림4차e-편한세상",
            "search_code":"3356",
            "apt_type":"아파트",
            "apt_year":19.0,
            "value_score":65.1871,
            "region":"서울시 구로구",
            "region_code":"Seoul",
            "sub_region_code":"1153000000_Seoul_Guro",
            "shorten_url":"https:\/\/me2.do\/55yYvTpq"
        },
        {
            "index":5,
            "sort":"balanced",
            "name":"벽산블루밍",
            "search_code":"3351",
            "apt_type":"아파트",
            "apt_year":19.0,
            "value_score":64.2138,
            "region":"서울시 구로구",
            "region_code":"Seoul",
            "sub_region_code":"1153000000_Seoul_Guro",
            "shorten_url":"https:\/\/me2.do\/55yYvTpq"
        },
        {
            "index":6,
            "sort":"balanced",
            "name":"신도림SK뷰(주상복합)",
            "search_code":"13085",
            "apt_type":"아파트",
            "apt_year":16.0,
            "value_score":64.0771,
            "region":"서울시 구로구",
            "region_code":"Seoul",
            "sub_region_code":"1153000000_Seoul_Guro",
            "shorten_url":"https:\/\/me2.do\/55yYvTpq"
        },
        {
            "index":7,
            "sort":"balanced",
            "name":"한마을",
            "search_code":"106",
            "apt_type":"아파트",
            "apt_year":23.0,
            "value_score":64.0138,
            "region":"서울시 구로구",
            "region_code":"Seoul",
            "sub_region_code":"1153000000_Seoul_Guro",
            "shorten_url":"https:\/\/me2.do\/55yYvTpq"
        },
        {
            "index":8,
            "sort":"balanced",
            "name":"신도림7차e-편한세상",
            "search_code":"8919",
            "apt_type":"아파트",
            "apt_year":18.0,
            "value_score":63.4371,
            "region":"서울시 구로구",
            "region_code":"Seoul",
            "sub_region_code":"1153000000_Seoul_Guro",
            "shorten_url":"https:\/\/me2.do\/55yYvTpq"
        },
        {
            "index":9,
            "sort":"balanced",
            "name":"신도림동아1차",
            "search_code":"1074",
            "apt_type":"아파트",
            "apt_year":23.0,
            "value_score":63.0171,
            "region":"서울시 구로구",
            "region_code":"Seoul",
            "sub_region_code":"1153000000_Seoul_Guro",
            "shorten_url":"https:\/\/me2.do\/55yYvTpq"
        },
        {
            "index":10,
            "sort":"living",
            "name":"디큐브시티(주상복합)",
            "search_code":"27310",
            "apt_type":"아파트",
            "apt_year":11.0,
            "value_score":73.4414,
            "region":"서울시 구로구",
            "region_code":"Seoul",
            "sub_region_code":"1153000000_Seoul_Guro",
            "shorten_url":"https:\/\/me2.do\/55yYvTpq"
        },
        {
            "index":11,
            "sort":"living",
            "name":"신도림태영타운",
            "search_code":"3204",
            "apt_type":"아파트",
            "apt_year":22.0,
            "value_score":68.7414,
            "region":"서울시 구로구",
            "region_code":"Seoul",
            "sub_region_code":"1153000000_Seoul_Guro",
            "shorten_url":"https:\/\/me2.do\/55yYvTpq"
        },
        {
            "index":12,
            "sort":"living",
            "name":"신도림동아3차",
            "search_code":"3210",
            "apt_type":"아파트",
            "apt_year":22.0,
            "value_score":66.0914,
            "region":"서울시 구로구",
            "region_code":"Seoul",
            "sub_region_code":"1153000000_Seoul_Guro",
            "shorten_url":"https:\/\/me2.do\/55yYvTpq"
        },
        {
            "index":13,
            "sort":"living",
            "name":"신도림4차e-편한세상",
            "search_code":"3356",
            "apt_type":"아파트",
            "apt_year":19.0,
            "value_score":65.9914,
            "region":"서울시 구로구",
            "region_code":"Seoul",
            "sub_region_code":"1153000000_Seoul_Guro",
            "shorten_url":"https:\/\/me2.do\/55yYvTpq"
        },
        {
            "index":14,
            "sort":"living",
            "name":"신도림대림1,2차(e편한세상)",
            "search_code":"3354",
            "apt_type":"아파트",
            "apt_year":23.0,
            "value_score":64.9414,
            "region":"서울시 구로구",
            "region_code":"Seoul",
            "sub_region_code":"1153000000_Seoul_Guro",
            "shorten_url":"https:\/\/me2.do\/55yYvTpq"
        },
        {
            "index":15,
            "sort":"living",
            "name":"벽산블루밍",
            "search_code":"3351",
            "apt_type":"아파트",
            "apt_year":19.0,
            "value_score":63.8592,
            "region":"서울시 구로구",
            "region_code":"Seoul",
            "sub_region_code":"1153000000_Seoul_Guro",
            "shorten_url":"https:\/\/me2.do\/55yYvTpq"
        },
        {
            "index":16,
            "sort":"living",
            "name":"한마을",
            "search_code":"106",
            "apt_type":"아파트",
            "apt_year":23.0,
            "value_score":63.2592,
            "region":"서울시 구로구",
            "region_code":"Seoul",
            "sub_region_code":"1153000000_Seoul_Guro",
            "shorten_url":"https:\/\/me2.do\/55yYvTpq"
        },
        {
            "index":17,
            "sort":"living",
            "name":"신도림동아1차",
            "search_code":"1074",
            "apt_type":"아파트",
            "apt_year":23.0,
            "value_score":62.7214,
            "region":"서울시 구로구",
            "region_code":"Seoul",
            "sub_region_code":"1153000000_Seoul_Guro",
            "shorten_url":"https:\/\/me2.do\/55yYvTpq"
        },
        {
            "index":18,
            "sort":"living",
            "name":"고척LIG리가",
            "search_code":"10312",
            "apt_type":"아파트",
            "apt_year":13.0,
            "value_score":61.8858,
            "region":"서울시 구로구",
            "region_code":"Seoul",
            "sub_region_code":"1153000000_Seoul_Guro",
            "shorten_url":"https:\/\/me2.do\/55yYvTpq"
        },
        {
            "index":19,
            "sort":"living",
            "name":"신도림7차e-편한세상",
            "search_code":"8919",
            "apt_type":"아파트",
            "apt_year":18.0,
            "value_score":61.8414,
            "region":"서울시 구로구",
            "region_code":"Seoul",
            "sub_region_code":"1153000000_Seoul_Guro",
            "shorten_url":"https:\/\/me2.do\/55yYvTpq"
        },
        {
            "index":20,
            "sort":"transport",
            "name":"디큐브시티(주상복합)",
            "search_code":"27310",
            "apt_type":"아파트",
            "apt_year":11.0,
            "value_score":77.56855,
            "region":"서울시 구로구",
            "region_code":"Seoul",
            "sub_region_code":"1153000000_Seoul_Guro",
            "shorten_url":"https:\/\/me2.do\/55yYvTpq"
        },
        {
            "index":21,
            "sort":"transport",
            "name":"신도림태영타운",
            "search_code":"3204",
            "apt_type":"아파트",
            "apt_year":22.0,
            "value_score":75.61855,
            "region":"서울시 구로구",
            "region_code":"Seoul",
            "sub_region_code":"1153000000_Seoul_Guro",
            "shorten_url":"https:\/\/me2.do\/55yYvTpq"
        },
        {
            "index":22,
            "sort":"transport",
            "name":"럭키",
            "search_code":"133",
            "apt_type":"아파트",
            "apt_year":30.0,
            "value_score":75.17135,
            "region":"서울시 구로구",
            "region_code":"Seoul",
            "sub_region_code":"1153000000_Seoul_Guro",
            "shorten_url":"https:\/\/me2.do\/55yYvTpq"
        },
        {
            "index":23,
            "sort":"transport",
            "name":"대림우성2차(주상복합)",
            "search_code":"1267",
            "apt_type":"아파트",
            "apt_year":35.0,
            "value_score":71.6604,
            "region":"서울시 구로구",
            "region_code":"Seoul",
            "sub_region_code":"1153000000_Seoul_Guro",
            "shorten_url":"https:\/\/me2.do\/55yYvTpq"
        },
        {
            "index":24,
            "sort":"transport",
            "name":"신도림4차e-편한세상",
            "search_code":"3356",
            "apt_type":"아파트",
            "apt_year":19.0,
            "value_score":70.89355,
            "region":"서울시 구로구",
            "region_code":"Seoul",
            "sub_region_code":"1153000000_Seoul_Guro",
            "shorten_url":"https:\/\/me2.do\/55yYvTpq"
        },
        {
            "index":25,
            "sort":"transport",
            "name":"구로SK뷰(주상복합)",
            "search_code":"17664",
            "apt_type":"아파트",
            "apt_year":16.0,
            "value_score":70.688,
            "region":"서울시 구로구",
            "region_code":"Seoul",
            "sub_region_code":"1153000000_Seoul_Guro",
            "shorten_url":"https:\/\/me2.do\/55yYvTpq"
        },
        {
            "index":26,
            "sort":"transport",
            "name":"신도림푸르지오2차(주상복합)",
            "search_code":"26829",
            "apt_type":"아파트",
            "apt_year":14.0,
            "value_score":70.44355,
            "region":"서울시 구로구",
            "region_code":"Seoul",
            "sub_region_code":"1153000000_Seoul_Guro",
            "shorten_url":"https:\/\/me2.do\/55yYvTpq"
        },
        {
            "index":27,
            "sort":"transport",
            "name":"신도림SK뷰(주상복합)",
            "search_code":"13085",
            "apt_type":"아파트",
            "apt_year":16.0,
            "value_score":70.33855,
            "region":"서울시 구로구",
            "region_code":"Seoul",
            "sub_region_code":"1153000000_Seoul_Guro",
            "shorten_url":"https:\/\/me2.do\/55yYvTpq"
        },
        {
            "index":28,
            "sort":"transport",
            "name":"경남아너스빌",
            "search_code":"100466",
            "apt_type":"아파트",
            "apt_year":13.0,
            "value_score":70.3354,
            "region":"서울시 구로구",
            "region_code":"Seoul",
            "sub_region_code":"1153000000_Seoul_Guro",
            "shorten_url":"https:\/\/me2.do\/55yYvTpq"
        },
        {
            "index":29,
            "sort":"transport",
            "name":"신도림동아1차",
            "search_code":"1074",
            "apt_type":"아파트",
            "apt_year":23.0,
            "value_score":69.54855,
            "region":"서울시 구로구",
            "region_code":"Seoul",
            "sub_region_code":"1153000000_Seoul_Guro",
            "shorten_url":"https:\/\/me2.do\/55yYvTpq"
        },
        {
            "index":30,
            "sort":"infra",
            "name":"디큐브시티(주상복합)",
            "search_code":"27310",
            "apt_type":"아파트",
            "apt_year":11.0,
            "value_score":72.53925,
            "region":"서울시 구로구",
            "region_code":"Seoul",
            "sub_region_code":"1153000000_Seoul_Guro",
            "shorten_url":"https:\/\/me2.do\/55yYvTpq"
        },
        {
            "index":31,
            "sort":"infra",
            "name":"신도림태영타운",
            "search_code":"3204",
            "apt_type":"아파트",
            "apt_year":22.0,
            "value_score":70.33925,
            "region":"서울시 구로구",
            "region_code":"Seoul",
            "sub_region_code":"1153000000_Seoul_Guro",
            "shorten_url":"https:\/\/me2.do\/55yYvTpq"
        },
        {
            "index":32,
            "sort":"infra",
            "name":"신도림동아3차",
            "search_code":"3210",
            "apt_type":"아파트",
            "apt_year":22.0,
            "value_score":68.33925,
            "region":"서울시 구로구",
            "region_code":"Seoul",
            "sub_region_code":"1153000000_Seoul_Guro",
            "shorten_url":"https:\/\/me2.do\/55yYvTpq"
        },
        {
            "index":33,
            "sort":"infra",
            "name":"신도림SK뷰(주상복합)",
            "search_code":"13085",
            "apt_type":"아파트",
            "apt_year":16.0,
            "value_score":67.73925,
            "region":"서울시 구로구",
            "region_code":"Seoul",
            "sub_region_code":"1153000000_Seoul_Guro",
            "shorten_url":"https:\/\/me2.do\/55yYvTpq"
        },
        {
            "index":34,
            "sort":"infra",
            "name":"신도림동아2차",
            "search_code":"3209",
            "apt_type":"아파트",
            "apt_year":22.0,
            "value_score":67.68925,
            "region":"서울시 구로구",
            "region_code":"Seoul",
            "sub_region_code":"1153000000_Seoul_Guro",
            "shorten_url":"https:\/\/me2.do\/55yYvTpq"
        },
        {
            "index":35,
            "sort":"infra",
            "name":"신도림대림1,2차(e편한세상)",
            "search_code":"3354",
            "apt_type":"아파트",
            "apt_year":23.0,
            "value_score":67.43925,
            "region":"서울시 구로구",
            "region_code":"Seoul",
            "sub_region_code":"1153000000_Seoul_Guro",
            "shorten_url":"https:\/\/me2.do\/55yYvTpq"
        },
        {
            "index":36,
            "sort":"infra",
            "name":"신도림4차e-편한세상",
            "search_code":"3356",
            "apt_type":"아파트",
            "apt_year":19.0,
            "value_score":66.48925,
            "region":"서울시 구로구",
            "region_code":"Seoul",
            "sub_region_code":"1153000000_Seoul_Guro",
            "shorten_url":"https:\/\/me2.do\/55yYvTpq"
        },
        {
            "index":37,
            "sort":"infra",
            "name":"신성은하수",
            "search_code":"1075",
            "apt_type":"아파트",
            "apt_year":25.0,
            "value_score":66.13925,
            "region":"서울시 구로구",
            "region_code":"Seoul",
            "sub_region_code":"1153000000_Seoul_Guro",
            "shorten_url":"https:\/\/me2.do\/55yYvTpq"
        },
        {
            "index":38,
            "sort":"infra",
            "name":"신도림롯데",
            "search_code":"132",
            "apt_type":"아파트",
            "apt_year":23.0,
            "value_score":65.78,
            "region":"서울시 구로구",
            "region_code":"Seoul",
            "sub_region_code":"1153000000_Seoul_Guro",
            "shorten_url":"https:\/\/me2.do\/55yYvTpq"
        },
        {
            "index":39,
            "sort":"infra",
            "name":"경남아너스빌",
            "search_code":"100466",
            "apt_type":"아파트",
            "apt_year":13.0,
            "value_score":65.734,
            "region":"서울시 구로구",
            "region_code":"Seoul",
            "sub_region_code":"1153000000_Seoul_Guro",
            "shorten_url":"https:\/\/me2.do\/55yYvTpq"
        },
        {
            "index":40,
            "sort":"education",
            "name":"디큐브시티(주상복합)",
            "search_code":"27310",
            "apt_type":"아파트",
            "apt_year":11.0,
            "value_score":71.4785,
            "region":"서울시 구로구",
            "region_code":"Seoul",
            "sub_region_code":"1153000000_Seoul_Guro",
            "shorten_url":"https:\/\/me2.do\/55yYvTpq"
        },
        {
            "index":41,
            "sort":"education",
            "name":"신도림동아3차",
            "search_code":"3210",
            "apt_type":"아파트",
            "apt_year":22.0,
            "value_score":67.2785,
            "region":"서울시 구로구",
            "region_code":"Seoul",
            "sub_region_code":"1153000000_Seoul_Guro",
            "shorten_url":"https:\/\/me2.do\/55yYvTpq"
        },
        {
            "index":42,
            "sort":"education",
            "name":"신도림태영타운",
            "search_code":"3204",
            "apt_type":"아파트",
            "apt_year":22.0,
            "value_score":67.0785,
            "region":"서울시 구로구",
            "region_code":"Seoul",
            "sub_region_code":"1153000000_Seoul_Guro",
            "shorten_url":"https:\/\/me2.do\/55yYvTpq"
        },
        {
            "index":43,
            "sort":"education",
            "name":"신도림대림1,2차(e편한세상)",
            "search_code":"3354",
            "apt_type":"아파트",
            "apt_year":23.0,
            "value_score":66.8785,
            "region":"서울시 구로구",
            "region_code":"Seoul",
            "sub_region_code":"1153000000_Seoul_Guro",
            "shorten_url":"https:\/\/me2.do\/55yYvTpq"
        },
        {
            "index":44,
            "sort":"education",
            "name":"신도림7차e-편한세상",
            "search_code":"8919",
            "apt_type":"아파트",
            "apt_year":18.0,
            "value_score":64.9785,
            "region":"서울시 구로구",
            "region_code":"Seoul",
            "sub_region_code":"1153000000_Seoul_Guro",
            "shorten_url":"https:\/\/me2.do\/55yYvTpq"
        },
        {
            "index":45,
            "sort":"education",
            "name":"신도림SK뷰(주상복합)",
            "search_code":"13085",
            "apt_type":"아파트",
            "apt_year":16.0,
            "value_score":63.0785,
            "region":"서울시 구로구",
            "region_code":"Seoul",
            "sub_region_code":"1153000000_Seoul_Guro",
            "shorten_url":"https:\/\/me2.do\/55yYvTpq"
        },
        {
            "index":46,
            "sort":"education",
            "name":"신도림동아2차",
            "search_code":"3209",
            "apt_type":"아파트",
            "apt_year":22.0,
            "value_score":62.9785,
            "region":"서울시 구로구",
            "region_code":"Seoul",
            "sub_region_code":"1153000000_Seoul_Guro",
            "shorten_url":"https:\/\/me2.do\/55yYvTpq"
        },
        {
            "index":47,
            "sort":"education",
            "name":"벽산블루밍",
            "search_code":"3351",
            "apt_type":"아파트",
            "apt_year":19.0,
            "value_score":62.373,
            "region":"서울시 구로구",
            "region_code":"Seoul",
            "sub_region_code":"1153000000_Seoul_Guro",
            "shorten_url":"https:\/\/me2.do\/55yYvTpq"
        },
        {
            "index":48,
            "sort":"education",
            "name":"한마을",
            "search_code":"106",
            "apt_type":"아파트",
            "apt_year":23.0,
            "value_score":62.373,
            "region":"서울시 구로구",
            "region_code":"Seoul",
            "sub_region_code":"1153000000_Seoul_Guro",
            "shorten_url":"https:\/\/me2.do\/55yYvTpq"
        },
        {
            "index":49,
            "sort":"education",
            "name":"신도림5차e-편한세상",
            "search_code":"8714",
            "apt_type":"아파트",
            "apt_year":19.0,
            "value_score":62.0690974047,
            "region":"서울시 구로구",
            "region_code":"Seoul",
            "sub_region_code":"1153000000_Seoul_Guro",
            "shorten_url":"https:\/\/me2.do\/55yYvTpq"
        }
    ]
}