{
    "schema":{
        "fields":[
            {
                "name":"index",
                "type":"integer"
            },
            {
                "name":"아파트명",
                "type":"string"
            },
            {
                "name":"코드",
                "type":"integer"
            },
            {
                "name":"타입",
                "type":"string"
            },
            {
                "name":"전용면적(m2)",
                "type":"number"
            },
            {
                "name":"전용면적(평)",
                "type":"string"
            },
            {
                "name":"법정동주소",
                "type":"string"
            },
            {
                "name":"도로명주소",
                "type":"string"
            },
            {
                "name":"최고층",
                "type":"number"
            },
            {
                "name":"최저층",
                "type":"number"
            },
            {
                "name":"매매실거래가",
                "type":"number"
            },
            {
                "name":"전세실거래가",
                "type":"number"
            },
            {
                "name":"전세가율",
                "type":"string"
            },
            {
                "name":"세대수",
                "type":"number"
            },
            {
                "name":"난방방식",
                "type":"string"
            },
            {
                "name":"방수",
                "type":"integer"
            },
            {
                "name":"욕실개수",
                "type":"integer"
            },
            {
                "name":"준공년월",
                "type":"string"
            },
            {
                "name":"준공년차",
                "type":"number"
            },
            {
                "name":"용적률",
                "type":"integer"
            },
            {
                "name":"건폐율",
                "type":"integer"
            },
            {
                "name":"최소공지가",
                "type":"number"
            },
            {
                "name":"최대공지가",
                "type":"number"
            },
            {
                "name":"y",
                "type":"number"
            },
            {
                "name":"x",
                "type":"number"
            }
        ],
        "primaryKey":[
            "index"
        ],
        "pandas_version":"1.4.0"
    },
    "data":[
        {
            "index":70,
            "아파트명":"LH트릴로채",
            "코드":127744,
            "타입":"APT",
            "전용면적(m2)":85.88,
            "전용면적(평)":"25평",
            "법정동주소":"충청북도 청주시 서원구 모충동 553",
            "도로명주소":"충청북도 청주시 서원구 쌍샘로 22",
            "최고층":29.0,
            "최저층":12.0,
            "매매실거래가":27000.0,
            "전세실거래가":24000.0,
            "전세가율":"71%",
            "세대수":1692.0,
            "난방방식":"지역난방",
            "방수":3,
            "욕실개수":2,
            "준공년월":"2021-11-01",
            "준공년차":1.0,
            "용적률":195,
            "건폐율":17,
            "최소공지가":null,
            "최대공지가":null,
            "y":36.628051,
            "x":127.479753
        },
        {
            "index":0,
            "아파트명":"개신광영(민간임대)",
            "코드":115036,
            "타입":"APT",
            "전용면적(m2)":51.12,
            "전용면적(평)":"15평",
            "법정동주소":"충청북도 청주시 서원구 개신동 1-19",
            "도로명주소":"충청북도 청주시 서원구 예체로7번길 33",
            "최고층":11.0,
            "최저층":9.0,
            "매매실거래가":null,
            "전세실거래가":8500.0,
            "전세가율":null,
            "세대수":110.0,
            "난방방식":"개별난방",
            "방수":2,
            "욕실개수":1,
            "준공년월":"1997-12-06",
            "준공년차":25.0,
            "용적률":201,
            "건폐율":25,
            "최소공지가":32100000.0,
            "최대공지가":35100000.0,
            "y":36.626288,
            "x":127.467244
        },
        {
            "index":1,
            "아파트명":"개신두진백로2차",
            "코드":7274,
            "타입":"APT",
            "전용면적(m2)":91.71,
            "전용면적(평)":"27평",
            "법정동주소":"충청북도 청주시 서원구 개신동 445",
            "도로명주소":"충청북도 청주시 서원구 모충로 38",
            "최고층":10.0,
            "최저층":6.0,
            "매매실거래가":9400.0,
            "전세실거래가":9500.0,
            "전세가율":null,
            "세대수":110.0,
            "난방방식":"개별난방",
            "방수":3,
            "욕실개수":1,
            "준공년월":"1993-12-03",
            "준공년차":29.0,
            "용적률":0,
            "건폐율":0,
            "최소공지가":56100000.0,
            "최대공지가":62600000.0,
            "y":36.624355,
            "x":127.468983
        },
        {
            "index":4,
            "아파트명":"개신우정",
            "코드":104955,
            "타입":"APT",
            "전용면적(m2)":35.05,
            "전용면적(평)":"10평",
            "법정동주소":"충청북도 청주시 서원구 개신동 1-16",
            "도로명주소":"충청북도 청주시 서원구 예체로1번길 29",
            "최고층":14.0,
            "최저층":6.0,
            "매매실거래가":3250.0,
            "전세실거래가":2000.0,
            "전세가율":null,
            "세대수":236.0,
            "난방방식":"개별난방",
            "방수":1,
            "욕실개수":1,
            "준공년월":"1997-07-25",
            "준공년차":25.0,
            "용적률":286,
            "건폐율":53,
            "최소공지가":17600000.0,
            "최대공지가":20800000.0,
            "y":36.625691,
            "x":127.46742
        },
        {
            "index":6,
            "아파트명":"개신재원",
            "코드":106605,
            "타입":"APT",
            "전용면적(m2)":43.38,
            "전용면적(평)":"13평",
            "법정동주소":"충청북도 청주시 서원구 개신동 447-3",
            "도로명주소":"충청북도 청주시 서원구 1순환로803번길 15",
            "최고층":10.0,
            "최저층":10.0,
            "매매실거래가":4500.0,
            "전세실거래가":3500.0,
            "전세가율":null,
            "세대수":180.0,
            "난방방식":"개별난방",
            "방수":1,
            "욕실개수":1,
            "준공년월":"1998-06-29",
            "준공년차":24.0,
            "용적률":252,
            "건폐율":28,
            "최소공지가":24300000.0,
            "최대공지가":29900000.0,
            "y":36.624172,
            "x":127.466402
        },
        {
            "index":8,
            "아파트명":"개신한사랑",
            "코드":106606,
            "타입":"APT",
            "전용면적(m2)":31.24,
            "전용면적(평)":"9평",
            "법정동주소":"충청북도 청주시 서원구 개신동 447-36",
            "도로명주소":"충청북도 청주시 서원구 모충로12번길 9-13",
            "최고층":12.0,
            "최저층":12.0,
            "매매실거래가":2800.0,
            "전세실거래가":3000.0,
            "전세가율":null,
            "세대수":138.0,
            "난방방식":"개별난방",
            "방수":1,
            "욕실개수":1,
            "준공년월":"1995-12-06",
            "준공년차":27.0,
            "용적률":352,
            "건폐율":48,
            "최소공지가":null,
            "최대공지가":null,
            "y":36.624786,
            "x":127.466565
        },
        {
            "index":231,
            "아파트명":"계룡리슈빌",
            "코드":25552,
            "타입":"APT",
            "전용면적(m2)":130.98,
            "전용면적(평)":"39평",
            "법정동주소":"충청북도 청주시 서원구 산남동 1102",
            "도로명주소":"충청북도 청주시 서원구 산남로 23",
            "최고층":15.0,
            "최저층":13.0,
            "매매실거래가":50000.0,
            "전세실거래가":35000.0,
            "전세가율":null,
            "세대수":551.0,
            "난방방식":"지역난방",
            "방수":3,
            "욕실개수":2,
            "준공년월":"2007-02-22",
            "준공년차":15.0,
            "용적률":199,
            "건폐율":17,
            "최소공지가":270000000.0,
            "최대공지가":316000000.0,
            "y":36.61043,
            "x":127.47103
        },
        {
            "index":251,
            "아파트명":"구룡산휴먼시아3단지",
            "코드":26806,
            "타입":"APT",
            "전용면적(m2)":106.38,
            "전용면적(평)":"32평",
            "법정동주소":"충청북도 청주시 서원구 성화동 616",
            "도로명주소":"충청북도 청주시 서원구 신성화로 8",
            "최고층":15.0,
            "최저층":10.0,
            "매매실거래가":27600.0,
            "전세실거래가":26500.0,
            "전세가율":"76~98%",
            "세대수":470.0,
            "난방방식":"지역난방",
            "방수":3,
            "욕실개수":2,
            "준공년월":"2009-05-04",
            "준공년차":13.0,
            "용적률":145,
            "건폐율":15,
            "최소공지가":160000000.0,
            "최대공지가":186000000.0,
            "y":36.616367,
            "x":127.460318
        },
        {
            "index":77,
            "아파트명":"그린맨션",
            "코드":15433,
            "타입":"APT",
            "전용면적(m2)":81.33,
            "전용면적(평)":"24평",
            "법정동주소":"충청북도 청주시 서원구 모충동 487-35",
            "도로명주소":"충청북도 청주시 서원구 모충로96번길 51",
            "최고층":6.0,
            "최저층":6.0,
            "매매실거래가":8000.0,
            "전세실거래가":8000.0,
            "전세가율":null,
            "세대수":96.0,
            "난방방식":"개별난방",
            "방수":3,
            "욕실개수":1,
            "준공년월":"1987-08-10",
            "준공년차":35.0,
            "용적률":0,
            "건폐율":0,
            "최소공지가":null,
            "최대공지가":null,
            "y":36.62489,
            "x":127.473664
        },
        {
            "index":79,
            "아파트명":"금호타운",
            "코드":7292,
            "타입":"APT",
            "전용면적(m2)":91.33,
            "전용면적(평)":"27평",
            "법정동주소":"충청북도 청주시 서원구 모충동 492",
            "도로명주소":"충청북도 청주시 서원구 쌍샘로107번길 12",
            "최고층":15.0,
            "최저층":10.0,
            "매매실거래가":14300.0,
            "전세실거래가":11000.0,
            "전세가율":null,
            "세대수":418.0,
            "난방방식":"개별난방",
            "방수":3,
            "욕실개수":2,
            "준공년월":"1995-02-24",
            "준공년차":27.0,
            "용적률":0,
            "건폐율":0,
            "최소공지가":73200000.0,
            "최대공지가":82000000.0,
            "y":36.62607,
            "x":127.471565
        },
        {
            "index":81,
            "아파트명":"남부(주상복합)",
            "코드":115066,
            "타입":"APT",
            "전용면적(m2)":65.42,
            "전용면적(평)":"19평",
            "법정동주소":"충청북도 청주시 서원구 모충동 88-4",
            "도로명주소":"충청북도 청주시 서원구 구룡산로405번길 54",
            "최고층":6.0,
            "최저층":6.0,
            "매매실거래가":3700.0,
            "전세실거래가":3300.0,
            "전세가율":null,
            "세대수":80.0,
            "난방방식":"개별난방",
            "방수":2,
            "욕실개수":1,
            "준공년월":"1981-05-16",
            "준공년차":41.0,
            "용적률":0,
            "건폐율":0,
            "최소공지가":null,
            "최대공지가":null,
            "y":36.620474,
            "x":127.489978
        },
        {
            "index":253,
            "아파트명":"남양휴튼",
            "코드":26188,
            "타입":"APT",
            "전용면적(m2)":129.91,
            "전용면적(평)":"39평",
            "법정동주소":"충청북도 청주시 서원구 성화동 436",
            "도로명주소":"충청북도 청주시 서원구 장전로 51",
            "최고층":20.0,
            "최저층":16.0,
            "매매실거래가":33800.0,
            "전세실거래가":36500.0,
            "전세가율":"79~99%",
            "세대수":577.0,
            "난방방식":"지역난방",
            "방수":3,
            "욕실개수":2,
            "준공년월":"2008-08-01",
            "준공년차":14.0,
            "용적률":219,
            "건폐율":18,
            "최소공지가":232000000.0,
            "최대공지가":273000000.0,
            "y":36.61827,
            "x":127.45403
        },
        {
            "index":270,
            "아파트명":"대림1차",
            "코드":15473,
            "타입":"APT",
            "전용면적(m2)":69.05,
            "전용면적(평)":"20평",
            "법정동주소":"충청북도 청주시 서원구 수곡동 154",
            "도로명주소":"충청북도 청주시 서원구 구룡산로 327",
            "최고층":5.0,
            "최저층":5.0,
            "매매실거래가":6000.0,
            "전세실거래가":5500.0,
            "전세가율":null,
            "세대수":115.0,
            "난방방식":"개별난방",
            "방수":3,
            "욕실개수":1,
            "준공년월":"1985-12-16",
            "준공년차":37.0,
            "용적률":0,
            "건폐율":0,
            "최소공지가":null,
            "최대공지가":null,
            "y":36.619236,
            "x":127.481204
        },
        {
            "index":276,
            "아파트명":"대림2차",
            "코드":7396,
            "타입":"APT",
            "전용면적(m2)":92.76,
            "전용면적(평)":"28평",
            "법정동주소":"충청북도 청주시 서원구 수곡동 239",
            "도로명주소":"충청북도 청주시 서원구 매봉로76번길 18",
            "최고층":5.0,
            "최저층":5.0,
            "매매실거래가":8800.0,
            "전세실거래가":7800.0,
            "전세가율":"82~83%",
            "세대수":120.0,
            "난방방식":"개별난방",
            "방수":3,
            "욕실개수":1,
            "준공년월":"1987-07-23",
            "준공년차":35.0,
            "용적률":0,
            "건폐율":0,
            "최소공지가":59500000.0,
            "최대공지가":65200000.0,
            "y":36.616566,
            "x":127.47864
        },
        {
            "index":123,
            "아파트명":"대승스카이빌",
            "코드":102106,
            "타입":"APT",
            "전용면적(m2)":50.66,
            "전용면적(평)":"15평",
            "법정동주소":"충청북도 청주시 서원구 분평동 275-1",
            "도로명주소":"충청북도 청주시 서원구 안뜸로12번길 13",
            "최고층":15.0,
            "최저층":15.0,
            "매매실거래가":7200.0,
            "전세실거래가":6500.0,
            "전세가율":null,
            "세대수":306.0,
            "난방방식":"개별난방",
            "방수":2,
            "욕실개수":1,
            "준공년월":"2001-06-26",
            "준공년차":21.0,
            "용적률":0,
            "건폐율":0,
            "최소공지가":38600000.0,
            "최대공지가":42200000.0,
            "y":36.611737,
            "x":127.479041
        },
        {
            "index":124,
            "아파트명":"대원",
            "코드":7513,
            "타입":"APT",
            "전용면적(m2)":82.8,
            "전용면적(평)":"25평",
            "법정동주소":"충청북도 청주시 서원구 분평동 1255",
            "도로명주소":"충청북도 청주시 서원구 분평로 49",
            "최고층":15.0,
            "최저층":11.0,
            "매매실거래가":18800.0,
            "전세실거래가":20000.0,
            "전세가율":"81~109%",
            "세대수":731.0,
            "난방방식":"지역난방",
            "방수":3,
            "욕실개수":2,
            "준공년월":"2000-10-28",
            "준공년차":22.0,
            "용적률":228,
            "건폐율":20,
            "최소공지가":115000000.0,
            "최대공지가":139000000.0,
            "y":36.609661,
            "x":127.490669
        },
        {
            "index":207,
            "아파트명":"대원칸타빌",
            "코드":24345,
            "타입":"APT",
            "전용면적(m2)":86.86,
            "전용면적(평)":"26평",
            "법정동주소":"충청북도 청주시 서원구 사창동 285-3",
            "도로명주소":"충청북도 청주시 서원구 예체로67번길 87",
            "최고층":25.0,
            "최저층":13.0,
            "매매실거래가":25500.0,
            "전세실거래가":23000.0,
            "전세가율":null,
            "세대수":810.0,
            "난방방식":"개별난방",
            "방수":3,
            "욕실개수":2,
            "준공년월":"2008-06-13",
            "준공년차":14.0,
            "용적률":247,
            "건폐율":16,
            "최소공지가":141000000.0,
            "최대공지가":170000000.0,
            "y":36.6325,
            "x":127.462565
        },
        {
            "index":237,
            "아파트명":"대원칸타빌1단지",
            "코드":25917,
            "타입":"APT",
            "전용면적(m2)":112.4,
            "전용면적(평)":"34평",
            "법정동주소":"충청북도 청주시 서원구 산남동 678",
            "도로명주소":"충청북도 청주시 서원구 두꺼비로 63",
            "최고층":15.0,
            "최저층":12.0,
            "매매실거래가":32500.0,
            "전세실거래가":30000.0,
            "전세가율":"68~103%",
            "세대수":600.0,
            "난방방식":"지역난방",
            "방수":3,
            "욕실개수":2,
            "준공년월":"2007-04-24",
            "준공년차":15.0,
            "용적률":192,
            "건폐율":20,
            "최소공지가":211000000.0,
            "최대공지가":248000000.0,
            "y":36.610377,
            "x":127.46292
        },
        {
            "index":239,
            "아파트명":"대원칸타빌2단지",
            "코드":25918,
            "타입":"APT",
            "전용면적(m2)":113.48,
            "전용면적(평)":"34평",
            "법정동주소":"충청북도 청주시 서원구 산남동 1100",
            "도로명주소":"충청북도 청주시 서원구 산미로 143",
            "최고층":14.0,
            "최저층":11.0,
            "매매실거래가":32000.0,
            "전세실거래가":26200.0,
            "전세가율":"58~97%",
            "세대수":518.0,
            "난방방식":"지역난방",
            "방수":3,
            "욕실개수":2,
            "준공년월":"2007-04-24",
            "준공년차":15.0,
            "용적률":192,
            "건폐율":0,
            "최소공지가":212000000.0,
            "최대공지가":244000000.0,
            "y":36.609808,
            "x":127.47475
        },
        {
            "index":11,
            "아파트명":"더샵청주그리니티",
            "코드":146899,
            "타입":"ABYG",
            "전용면적(m2)":85.25,
            "전용면적(평)":"25평",
            "법정동주소":"충청북도 청주시 서원구 개신동 산104-6번지 일원",
            "도로명주소":"충청북도 청주시 서원구",
            "최고층":38.0,
            "최저층":30.0,
            "매매실거래가":null,
            "전세실거래가":null,
            "전세가율":"67~69%",
            "세대수":1191.0,
            "난방방식":"개별난방",
            "방수":3,
            "욕실개수":2,
            "준공년월":"2026-01-01",
            "준공년차":-4.0,
            "용적률":229,
            "건폐율":10,
            "최소공지가":null,
            "최대공지가":null,
            "y":36.621809,
            "x":127.464585
        },
        {
            "index":279,
            "아파트명":"더샵청주퍼스트파크",
            "코드":120999,
            "타입":"APT",
            "전용면적(m2)":83.47,
            "전용면적(평)":"25평",
            "법정동주소":"충청북도 청주시 서원구 수곡동 1057",
            "도로명주소":"충청북도 청주시 서원구 수곡로 20",
            "최고층":28.0,
            "최저층":15.0,
            "매매실거래가":24117.0,
            "전세실거래가":33000.0,
            "전세가율":"67~90%",
            "세대수":1112.0,
            "난방방식":"개별난방",
            "방수":3,
            "욕실개수":2,
            "준공년월":"2021-03-01",
            "준공년차":1.0,
            "용적률":226,
            "건폐율":17,
            "최소공지가":196000000.0,
            "최대공지가":218000000.0,
            "y":36.614962,
            "x":127.476725
        },
        {
            "index":181,
            "아파트명":"덕희아파트",
            "코드":112872,
            "타입":"APT",
            "전용면적(m2)":31.84,
            "전용면적(평)":"9평",
            "법정동주소":"충청북도 청주시 서원구 사직동 358-5",
            "도로명주소":"충청북도 청주시 서원구 남사로 14",
            "최고층":12.0,
            "최저층":12.0,
            "매매실거래가":2600.0,
            "전세실거래가":3000.0,
            "전세가율":"69~155%",
            "세대수":203.0,
            "난방방식":"개별난방",
            "방수":1,
            "욕실개수":1,
            "준공년월":"1994-02-18",
            "준공년차":28.0,
            "용적률":257,
            "건폐율":23,
            "최소공지가":13500000.0,
            "최대공지가":16300000.0,
            "y":36.629803,
            "x":127.478126
        },
        {
            "index":182,
            "아파트명":"두산위브더제니스(주상복합)",
            "코드":24884,
            "타입":"APT",
            "전용면적(m2)":130.14,
            "전용면적(평)":"39평",
            "법정동주소":"충청북도 청주시 서원구 사직동 265-5",
            "도로명주소":"충청북도 청주시 서원구 사운로 93",
            "최고층":41.0,
            "최저층":34.0,
            "매매실거래가":33250.0,
            "전세실거래가":24000.0,
            "전세가율":null,
            "세대수":576.0,
            "난방방식":"개별난방",
            "방수":3,
            "욕실개수":2,
            "준공년월":"2009-07-29",
            "준공년차":13.0,
            "용적률":672,
            "건폐율":34,
            "최소공지가":null,
            "최대공지가":null,
            "y":36.637201,
            "x":127.477908
        },
        {
            "index":87,
            "아파트명":"두산한솔",
            "코드":7295,
            "타입":"APT",
            "전용면적(m2)":78.84,
            "전용면적(평)":"23평",
            "법정동주소":"충청북도 청주시 서원구 모충동 473",
            "도로명주소":"충청북도 청주시 서원구 모충로124번길 53",
            "최고층":15.0,
            "최저층":8.0,
            "매매실거래가":13300.0,
            "전세실거래가":12000.0,
            "전세가율":null,
            "세대수":392.0,
            "난방방식":"개별난방",
            "방수":3,
            "욕실개수":1,
            "준공년월":"1994-10-31",
            "준공년차":28.0,
            "용적률":0,
            "건폐율":0,
            "최소공지가":68200000.0,
            "최대공지가":80300000.0,
            "y":36.625931,
            "x":127.476911
        },
        {
            "index":19,
            "아파트명":"두산한솔1차",
            "코드":7265,
            "타입":"APT",
            "전용면적(m2)":83.02,
            "전용면적(평)":"25평",
            "법정동주소":"충청북도 청주시 서원구 개신동 447-15",
            "도로명주소":"충청북도 청주시 서원구 모충로26번길 22",
            "최고층":15.0,
            "최저층":14.0,
            "매매실거래가":14200.0,
            "전세실거래가":5000.0,
            "전세가율":null,
            "세대수":206.0,
            "난방방식":"개별난방",
            "방수":3,
            "욕실개수":1,
            "준공년월":"1993-05-26",
            "준공년차":29.0,
            "용적률":0,
            "건폐율":0,
            "최소공지가":73300000.0,
            "최대공지가":81000000.0,
            "y":36.62345,
            "x":127.4668
        },
        {
            "index":22,
            "아파트명":"두산한솔2차",
            "코드":7267,
            "타입":"APT",
            "전용면적(m2)":81.01,
            "전용면적(평)":"24평",
            "법정동주소":"충청북도 청주시 서원구 개신동 444-2",
            "도로명주소":"충청북도 청주시 서원구 모충로26번길 60",
            "최고층":15.0,
            "최저층":15.0,
            "매매실거래가":9800.0,
            "전세실거래가":9500.0,
            "전세가율":null,
            "세대수":180.0,
            "난방방식":"개별난방",
            "방수":3,
            "욕실개수":1,
            "준공년월":"1993-11-12",
            "준공년차":29.0,
            "용적률":0,
            "건폐율":0,
            "최소공지가":66000000.0,
            "최대공지가":73300000.0,
            "y":36.623614,
            "x":127.468485
        },
        {
            "index":24,
            "아파트명":"두진백로1단지",
            "코드":7270,
            "타입":"APT",
            "전용면적(m2)":103.41,
            "전용면적(평)":"31평",
            "법정동주소":"충청북도 청주시 서원구 개신동 443",
            "도로명주소":"충청북도 청주시 서원구 모충로 38",
            "최고층":15.0,
            "최저층":10.0,
            "매매실거래가":15000.0,
            "전세실거래가":12500.0,
            "전세가율":null,
            "세대수":227.0,
            "난방방식":"개별난방",
            "방수":3,
            "욕실개수":2,
            "준공년월":"1993-04-12",
            "준공년차":29.0,
            "용적률":385,
            "건폐율":23,
            "최소공지가":79300000.0,
            "최대공지가":91100000.0,
            "y":36.624803,
            "x":127.468421
        },
        {
            "index":288,
            "아파트명":"두진하트리움",
            "코드":12824,
            "타입":"APT",
            "전용면적(m2)":73.96,
            "전용면적(평)":"22평",
            "법정동주소":"충청북도 청주시 서원구 수곡동 1002",
            "도로명주소":"충청북도 청주시 서원구 수곡로 36",
            "최고층":15.0,
            "최저층":10.0,
            "매매실거래가":16200.0,
            "전세실거래가":15000.0,
            "전세가율":"85~104%",
            "세대수":935.0,
            "난방방식":"지역난방",
            "방수":3,
            "욕실개수":1,
            "준공년월":"1995-05-02",
            "준공년차":27.0,
            "용적률":215,
            "건폐율":19,
            "최소공지가":81300000.0,
            "최대공지가":92900000.0,
            "y":36.616135,
            "x":127.474897
        },
        {
            "index":126,
            "아파트명":"럭키",
            "코드":11630,
            "타입":"APT",
            "전용면적(m2)":93.95,
            "전용면적(평)":"28평",
            "법정동주소":"충청북도 청주시 서원구 분평동 252-42",
            "도로명주소":"충청북도 청주시 서원구 안뜸로39번길 5-1",
            "최고층":15.0,
            "최저층":6.0,
            "매매실거래가":12500.0,
            "전세실거래가":13000.0,
            "전세가율":null,
            "세대수":156.0,
            "난방방식":"개별난방",
            "방수":3,
            "욕실개수":2,
            "준공년월":"1992-11-19",
            "준공년차":30.0,
            "용적률":0,
            "건폐율":0,
            "최소공지가":67600000.0,
            "최대공지가":77400000.0,
            "y":36.6125,
            "x":127.48095
        },
        {
            "index":292,
            "아파트명":"모란",
            "코드":7399,
            "타입":"APT",
            "전용면적(m2)":66.12,
            "전용면적(평)":"20평",
            "법정동주소":"충청북도 청주시 서원구 수곡동 197-9",
            "도로명주소":"충청북도 청주시 서원구 구룡산로338번길 23-10",
            "최고층":5.0,
            "최저층":5.0,
            "매매실거래가":6300.0,
            "전세실거래가":5000.0,
            "전세가율":null,
            "세대수":110.0,
            "난방방식":"개별난방",
            "방수":3,
            "욕실개수":1,
            "준공년월":"1979-06-01",
            "준공년차":43.0,
            "용적률":0,
            "건폐율":0,
            "최소공지가":35500000.0,
            "최대공지가":40700000.0,
            "y":36.616824,
            "x":127.481981
        },
        {
            "index":90,
            "아파트명":"모충동일센타시아",
            "코드":110869,
            "타입":"APT",
            "전용면적(m2)":85.35,
            "전용면적(평)":"25평",
            "법정동주소":"충청북도 청주시 서원구 모충동 552",
            "도로명주소":"충청북도 청주시 서원구 매봉로 190",
            "최고층":19.0,
            "최저층":10.0,
            "매매실거래가":19500.0,
            "전세실거래가":16275.0,
            "전세가율":"88~95%",
            "세대수":240.0,
            "난방방식":"개별난방",
            "방수":3,
            "욕실개수":2,
            "준공년월":"2016-05-03",
            "준공년차":6.0,
            "용적률":226,
            "건폐율":20,
            "최소공지가":108000000.0,
            "최대공지가":124000000.0,
            "y":36.626211,
            "x":127.476387
        },
        {
            "index":93,
            "아파트명":"모충청송",
            "코드":15434,
            "타입":"APT",
            "전용면적(m2)":80.55,
            "전용면적(평)":"24평",
            "법정동주소":"충청북도 청주시 서원구 모충동 342",
            "도로명주소":"충청북도 청주시 서원구 모충로 164",
            "최고층":15.0,
            "최저층":11.0,
            "매매실거래가":10000.0,
            "전세실거래가":6500.0,
            "전세가율":"71~115%",
            "세대수":94.0,
            "난방방식":"개별난방",
            "방수":3,
            "욕실개수":1,
            "준공년월":"1994-07-26",
            "준공년차":28.0,
            "용적률":274,
            "건폐율":23,
            "최소공지가":59100000.0,
            "최대공지가":64700000.0,
            "y":36.62876,
            "x":127.48081
        },
        {
            "index":187,
            "아파트명":"미호",
            "코드":105216,
            "타입":"APT",
            "전용면적(m2)":81.53,
            "전용면적(평)":"24평",
            "법정동주소":"충청북도 청주시 서원구 사직동 265-7",
            "도로명주소":"충청북도 청주시 서원구 사운로99번길 23",
            "최고층":6.0,
            "최저층":6.0,
            "매매실거래가":8900.0,
            "전세실거래가":8000.0,
            "전세가율":null,
            "세대수":110.0,
            "난방방식":"개별난방",
            "방수":3,
            "욕실개수":1,
            "준공년월":"1979-10-01",
            "준공년차":43.0,
            "용적률":0,
            "건폐율":0,
            "최소공지가":null,
            "최대공지가":null,
            "y":36.637525,
            "x":127.477343
        },
        {
            "index":328,
            "아파트명":"보람",
            "코드":144358,
            "타입":"APT",
            "전용면적(m2)":51.11,
            "전용면적(평)":"15평",
            "법정동주소":"충청북도 청주시 서원구 장성동 4-2",
            "도로명주소":"충청북도 청주시 서원구 궁뜰로 47-1",
            "최고층":4.0,
            "최저층":4.0,
            "매매실거래가":null,
            "전세실거래가":null,
            "전세가율":null,
            "세대수":88.0,
            "난방방식":"개별난방",
            "방수":2,
            "욕실개수":1,
            "준공년월":"1992-01-25",
            "준공년차":30.0,
            "용적률":0,
            "건폐율":0,
            "최소공지가":null,
            "최대공지가":null,
            "y":36.599248,
            "x":127.482436
        },
        {
            "index":128,
            "아파트명":"보성",
            "코드":13988,
            "타입":"APT",
            "전용면적(m2)":95.22,
            "전용면적(평)":"28평",
            "법정동주소":"충청북도 청주시 서원구 분평동 301-2",
            "도로명주소":"충청북도 청주시 서원구 청남로2005번길 70",
            "최고층":14.0,
            "최저층":8.0,
            "매매실거래가":16900.0,
            "전세실거래가":10000.0,
            "전세가율":"68~72%",
            "세대수":155.0,
            "난방방식":"개별난방",
            "방수":3,
            "욕실개수":2,
            "준공년월":"1992-12-24",
            "준공년차":30.0,
            "용적률":0,
            "건폐율":0,
            "최소공지가":null,
            "최대공지가":null,
            "y":36.610456,
            "x":127.480749
        },
        {
            "index":242,
            "아파트명":"부영사랑으로",
            "코드":26054,
            "타입":"APT",
            "전용면적(m2)":88.49,
            "전용면적(평)":"26평",
            "법정동주소":"충청북도 청주시 서원구 산남동 1094",
            "도로명주소":"충청북도 청주시 서원구 원흥로 14",
            "최고층":15.0,
            "최저층":13.0,
            "매매실거래가":21900.0,
            "전세실거래가":20000.0,
            "전세가율":"73~115%",
            "세대수":985.0,
            "난방방식":"지역난방",
            "방수":3,
            "욕실개수":2,
            "준공년월":"2007-04-26",
            "준공년차":15.0,
            "용적률":193,
            "건폐율":19,
            "최소공지가":130000000.0,
            "최대공지가":162000000.0,
            "y":36.608457,
            "x":127.472937
        },
        {
            "index":131,
            "아파트명":"분평계룡리슈빌",
            "코드":26496,
            "타입":"APT",
            "전용면적(m2)":132.05,
            "전용면적(평)":"39평",
            "법정동주소":"충청북도 청주시 서원구 분평동 274",
            "도로명주소":"충청북도 청주시 서원구 매봉로 26-1",
            "최고층":15.0,
            "최저층":12.0,
            "매매실거래가":29300.0,
            "전세실거래가":25000.0,
            "전세가율":null,
            "세대수":173.0,
            "난방방식":"개별난방",
            "방수":3,
            "욕실개수":2,
            "준공년월":"2008-07-30",
            "준공년차":14.0,
            "용적률":209,
            "건폐율":19,
            "최소공지가":196000000.0,
            "최대공지가":228000000.0,
            "y":36.6127,
            "x":127.47856
        },
        {
            "index":134,
            "아파트명":"분평계룡리슈빌2단지",
            "코드":26495,
            "타입":"APT",
            "전용면적(m2)":130.54,
            "전용면적(평)":"39평",
            "법정동주소":"충청북도 청주시 서원구 분평동 262",
            "도로명주소":"충청북도 청주시 서원구 매봉로 28",
            "최고층":15.0,
            "최저층":15.0,
            "매매실거래가":32000.0,
            "전세실거래가":33000.0,
            "전세가율":null,
            "세대수":150.0,
            "난방방식":"개별난방",
            "방수":3,
            "욕실개수":2,
            "준공년월":"2008-07-30",
            "준공년차":14.0,
            "용적률":218,
            "건폐율":19,
            "최소공지가":184000000.0,
            "최대공지가":214000000.0,
            "y":36.613211,
            "x":127.478014
        },
        {
            "index":294,
            "아파트명":"산남세원청실",
            "코드":7401,
            "타입":"APT",
            "전용면적(m2)":84.37,
            "전용면적(평)":"25평",
            "법정동주소":"충청북도 청주시 서원구 수곡동 1001",
            "도로명주소":"충청북도 청주시 서원구 수곡로 46",
            "최고층":15.0,
            "최저층":12.0,
            "매매실거래가":16500.0,
            "전세실거래가":15000.0,
            "전세가율":null,
            "세대수":417.0,
            "난방방식":"개별난방",
            "방수":3,
            "욕실개수":1,
            "준공년월":"1995-05-08",
            "준공년차":27.0,
            "용적률":221,
            "건폐율":18,
            "최소공지가":92500000.0,
            "최대공지가":106000000.0,
            "y":36.616772,
            "x":127.474144
        },
        {
            "index":296,
            "아파트명":"산남주공3차",
            "코드":7410,
            "타입":"APT",
            "전용면적(m2)":57.15,
            "전용면적(평)":"17평",
            "법정동주소":"충청북도 청주시 서원구 수곡동 337",
            "도로명주소":"충청북도 청주시 서원구 매봉로 82",
            "최고층":15.0,
            "최저층":5.0,
            "매매실거래가":5500.0,
            "전세실거래가":7800.0,
            "전세가율":"71~82%",
            "세대수":510.0,
            "난방방식":"개별난방",
            "방수":2,
            "욕실개수":1,
            "준공년월":"1991-11-28",
            "준공년차":31.0,
            "용적률":0,
            "건폐율":0,
            "최소공지가":45000000.0,
            "최대공지가":53500000.0,
            "y":36.617876,
            "x":127.479223
        },
        {
            "index":300,
            "아파트명":"산남주공4단지",
            "코드":7418,
            "타입":"APT",
            "전용면적(m2)":50.39,
            "전용면적(평)":"15평",
            "법정동주소":"충청북도 청주시 서원구 수곡동 314",
            "도로명주소":"충청북도 청주시 서원구 구룡산로 275-13",
            "최고층":15.0,
            "최저층":15.0,
            "매매실거래가":7000.0,
            "전세실거래가":7000.0,
            "전세가율":null,
            "세대수":1005.0,
            "난방방식":"지역난방",
            "방수":2,
            "욕실개수":1,
            "준공년월":"1993-07-31",
            "준공년차":29.0,
            "용적률":148,
            "건폐율":11,
            "최소공지가":40000000.0,
            "최대공지가":45000000.0,
            "y":36.61973,
            "x":127.474627
        },
        {
            "index":243,
            "아파트명":"산남퀸덤",
            "코드":25844,
            "타입":"APT",
            "전용면적(m2)":112.43,
            "전용면적(평)":"34평",
            "법정동주소":"충청북도 청주시 서원구 산남동 671",
            "도로명주소":"충청북도 청주시 서원구 두꺼비로 93",
            "최고층":15.0,
            "최저층":12.0,
            "매매실거래가":26500.0,
            "전세실거래가":24100.0,
            "전세가율":"65~97%",
            "세대수":570.0,
            "난방방식":"지역난방",
            "방수":3,
            "욕실개수":2,
            "준공년월":"2007-01-02",
            "준공년차":15.0,
            "용적률":199,
            "건폐율":19,
            "최소공지가":182000000.0,
            "최대공지가":224000000.0,
            "y":36.612747,
            "x":127.462892
        },
        {
            "index":94,
            "아파트명":"삼덕",
            "코드":112518,
            "타입":"APT",
            "전용면적(m2)":42.68,
            "전용면적(평)":"12평",
            "법정동주소":"충청북도 청주시 서원구 모충동 490-1",
            "도로명주소":"충청북도 청주시 서원구 쌍샘로107번길 25",
            "최고층":9.0,
            "최저층":5.0,
            "매매실거래가":3500.0,
            "전세실거래가":2400.0,
            "전세가율":null,
            "세대수":84.0,
            "난방방식":"개별난방",
            "방수":1,
            "욕실개수":1,
            "준공년월":"1997-03-28",
            "준공년차":25.0,
            "용적률":193,
            "건폐율":25,
            "최소공지가":null,
            "최대공지가":null,
            "y":36.625679,
            "x":127.472775
        },
        {
            "index":31,
            "아파트명":"삼익",
            "코드":7279,
            "타입":"APT",
            "전용면적(m2)":104.48,
            "전용면적(평)":"31평",
            "법정동주소":"충청북도 청주시 서원구 개신동 10",
            "도로명주소":"충청북도 청주시 서원구 예체로29번길 9",
            "최고층":15.0,
            "최저층":13.0,
            "매매실거래가":15000.0,
            "전세실거래가":17000.0,
            "전세가율":"83~103%",
            "세대수":744.0,
            "난방방식":"지역난방",
            "방수":3,
            "욕실개수":2,
            "준공년월":"1991-02-27",
            "준공년차":31.0,
            "용적률":210,
            "건폐율":17,
            "최소공지가":101000000.0,
            "최대공지가":117000000.0,
            "y":36.627374,
            "x":127.46686
        },
        {
            "index":34,
            "아파트명":"삼익2차",
            "코드":15428,
            "타입":"APT",
            "전용면적(m2)":103.38,
            "전용면적(평)":"31평",
            "법정동주소":"충청북도 청주시 서원구 개신동 11",
            "도로명주소":"충청북도 청주시 서원구 창직로12번길 65",
            "최고층":13.0,
            "최저층":9.0,
            "매매실거래가":16800.0,
            "전세실거래가":13000.0,
            "전세가율":null,
            "세대수":390.0,
            "난방방식":"지역난방",
            "방수":3,
            "욕실개수":2,
            "준공년월":"1993-02-22",
            "준공년차":29.0,
            "용적률":193,
            "건폐율":18,
            "최소공지가":90700000.0,
            "최대공지가":104000000.0,
            "y":36.62853,
            "x":127.46444
        },
        {
            "index":95,
            "아파트명":"삼익세라믹",
            "코드":7300,
            "타입":"APT",
            "전용면적(m2)":73.47,
            "전용면적(평)":"22평",
            "법정동주소":"충청북도 청주시 서원구 모충동 374-1",
            "도로명주소":"충청북도 청주시 서원구 서원서로 27",
            "최고층":15.0,
            "최저층":8.0,
            "매매실거래가":9300.0,
            "전세실거래가":7000.0,
            "전세가율":null,
            "세대수":229.0,
            "난방방식":"개별난방",
            "방수":2,
            "욕실개수":1,
            "준공년월":"1989-08-25",
            "준공년차":33.0,
            "용적률":0,
            "건폐율":0,
            "최소공지가":null,
            "최대공지가":null,
            "y":36.624597,
            "x":127.478865
        },
        {
            "index":308,
            "아파트명":"삼일맨션",
            "코드":106719,
            "타입":"APT",
            "전용면적(m2)":100.52,
            "전용면적(평)":"30평",
            "법정동주소":"충청북도 청주시 서원구 수곡동 153-3",
            "도로명주소":"충청북도 청주시 서원구 구룡산로337번길 33",
            "최고층":6.0,
            "최저층":5.0,
            "매매실거래가":10500.0,
            "전세실거래가":7500.0,
            "전세가율":null,
            "세대수":87.0,
            "난방방식":"개별난방",
            "방수":3,
            "욕실개수":2,
            "준공년월":"1986-09-15",
            "준공년차":36.0,
            "용적률":0,
            "건폐율":0,
            "최소공지가":63700000.0,
            "최대공지가":66500000.0,
            "y":36.620158,
            "x":127.481947
        },
        {
            "index":99,
            "아파트명":"삼호",
            "코드":7303,
            "타입":"APT",
            "전용면적(m2)":96.61,
            "전용면적(평)":"29평",
            "법정동주소":"충청북도 청주시 서원구 모충동 446-20",
            "도로명주소":"충청북도 청주시 서원구 매봉로 208",
            "최고층":15.0,
            "최저층":9.0,
            "매매실거래가":13300.0,
            "전세실거래가":7000.0,
            "전세가율":null,
            "세대수":254.0,
            "난방방식":"개별난방",
            "방수":3,
            "욕실개수":1,
            "준공년월":"1991-08-21",
            "준공년차":31.0,
            "용적률":0,
            "건폐율":0,
            "최소공지가":68900000.0,
            "최대공지가":78000000.0,
            "y":36.627991,
            "x":127.476092
        },
        {
            "index":37,
            "아파트명":"서우",
            "코드":115043,
            "타입":"APT",
            "전용면적(m2)":34.91,
            "전용면적(평)":"10평",
            "법정동주소":"충청북도 청주시 서원구 개신동 443-6",
            "도로명주소":"충청북도 청주시 서원구 모충로 44-2",
            "최고층":4.0,
            "최저층":4.0,
            "매매실거래가":null,
            "전세실거래가":null,
            "전세가율":null,
            "세대수":88.0,
            "난방방식":"개별난방",
            "방수":2,
            "욕실개수":1,
            "준공년월":"1987-12-29",
            "준공년차":35.0,
            "용적률":0,
            "건폐율":0,
            "최소공지가":16200000.0,
            "최대공지가":18000000.0,
            "y":36.625138,
            "x":127.469692
        },
        {
            "index":210,
            "아파트명":"서울",
            "코드":106568,
            "타입":"APT",
            "전용면적(m2)":66.29,
            "전용면적(평)":"20평",
            "법정동주소":"충청북도 청주시 서원구 사창동 372-3",
            "도로명주소":"충청북도 청주시 서원구 창직로 1",
            "최고층":5.0,
            "최저층":5.0,
            "매매실거래가":8400.0,
            "전세실거래가":7000.0,
            "전세가율":null,
            "세대수":100.0,
            "난방방식":"개별난방",
            "방수":2,
            "욕실개수":1,
            "준공년월":"1978-11-14",
            "준공년차":44.0,
            "용적률":0,
            "건폐율":0,
            "최소공지가":null,
            "최대공지가":null,
            "y":36.631109,
            "x":127.461881
        },
        {
            "index":102,
            "아파트명":"서원",
            "코드":105702,
            "타입":"APT",
            "전용면적(m2)":32.39,
            "전용면적(평)":"9평",
            "법정동주소":"충청북도 청주시 서원구 모충동 117-2",
            "도로명주소":"충청북도 청주시 서원구 구룡산로389번길 79",
            "최고층":5.0,
            "최저층":5.0,
            "매매실거래가":4000.0,
            "전세실거래가":null,
            "전세가율":null,
            "세대수":89.0,
            "난방방식":"개별난방",
            "방수":1,
            "욕실개수":1,
            "준공년월":"1987-10-30",
            "준공년차":35.0,
            "용적률":188,
            "건폐율":37,
            "최소공지가":24900000.0,
            "최대공지가":28900000.0,
            "y":36.621999,
            "x":127.488643
        },
        {
            "index":310,
            "아파트명":"선광한빛(로즈웰타운)",
            "코드":126786,
            "타입":"APT",
            "전용면적(m2)":39.67,
            "전용면적(평)":"12평",
            "법정동주소":"충청북도 청주시 서원구 수곡동 231-2",
            "도로명주소":"충청북도 청주시 서원구 매봉로60번길 18",
            "최고층":15.0,
            "최저층":11.0,
            "매매실거래가":null,
            "전세실거래가":3150.0,
            "전세가율":null,
            "세대수":377.0,
            "난방방식":"개별난방",
            "방수":1,
            "욕실개수":1,
            "준공년월":"1998-03-31",
            "준공년차":24.0,
            "용적률":311,
            "건폐율":23,
            "최소공지가":24800000.0,
            "최대공지가":27400000.0,
            "y":36.615027,
            "x":127.478844
        },
        {
            "index":258,
            "아파트명":"성화호반베르디움",
            "코드":101838,
            "타입":"APT",
            "전용면적(m2)":110.01,
            "전용면적(평)":"33평",
            "법정동주소":"충청북도 청주시 서원구 성화동 939",
            "도로명주소":"충청북도 청주시 서원구 구룡산로 24",
            "최고층":20.0,
            "최저층":10.0,
            "매매실거래가":37500.0,
            "전세실거래가":34000.0,
            "전세가율":"72~100%",
            "세대수":840.0,
            "난방방식":"개별난방",
            "방수":3,
            "욕실개수":2,
            "준공년월":"2012-06-25",
            "준공년차":10.0,
            "용적률":180,
            "건폐율":16,
            "최소공지가":246000000.0,
            "최대공지가":279000000.0,
            "y":36.614346,
            "x":127.447957
        },
        {
            "index":311,
            "아파트명":"세원1차",
            "코드":15467,
            "타입":"APT",
            "전용면적(m2)":71.1,
            "전용면적(평)":"21평",
            "법정동주소":"충청북도 청주시 서원구 수곡동 40-1",
            "도로명주소":"충청북도 청주시 서원구 수영로47번길 19",
            "최고층":5.0,
            "최저층":5.0,
            "매매실거래가":7300.0,
            "전세실거래가":5500.0,
            "전세가율":null,
            "세대수":90.0,
            "난방방식":"개별난방",
            "방수":3,
            "욕실개수":1,
            "준공년월":"1989-06-14",
            "준공년차":33.0,
            "용적률":0,
            "건폐율":0,
            "최소공지가":45500000.0,
            "최대공지가":51100000.0,
            "y":36.616401,
            "x":127.490558
        },
        {
            "index":314,
            "아파트명":"세원2차",
            "코드":15468,
            "타입":"APT",
            "전용면적(m2)":71.55,
            "전용면적(평)":"21평",
            "법정동주소":"충청북도 청주시 서원구 수곡동 60-1",
            "도로명주소":"충청북도 청주시 서원구 수영로24번길 5",
            "최고층":6.0,
            "최저층":6.0,
            "매매실거래가":6400.0,
            "전세실거래가":9500.0,
            "전세가율":null,
            "세대수":120.0,
            "난방방식":"개별난방",
            "방수":3,
            "욕실개수":1,
            "준공년월":"1989-12-08",
            "준공년차":33.0,
            "용적률":0,
            "건폐율":0,
            "최소공지가":44300000.0,
            "최대공지가":50100000.0,
            "y":36.61498,
            "x":127.489013
        },
        {
            "index":317,
            "아파트명":"세원홍실",
            "코드":13013,
            "타입":"APT",
            "전용면적(m2)":116.01,
            "전용면적(평)":"35평",
            "법정동주소":"충청북도 청주시 서원구 수곡동 776",
            "도로명주소":"충청북도 청주시 서원구 수곡로 88",
            "최고층":15.0,
            "최저층":13.0,
            "매매실거래가":22900.0,
            "전세실거래가":20000.0,
            "전세가율":null,
            "세대수":224.0,
            "난방방식":"지역난방",
            "방수":3,
            "욕실개수":2,
            "준공년월":"1996-09-04",
            "준공년차":26.0,
            "용적률":220,
            "건폐율":20,
            "최소공지가":116000000.0,
            "최대공지가":136000000.0,
            "y":36.61978,
            "x":127.4722
        },
        {
            "index":41,
            "아파트명":"송학삼익맨션",
            "코드":7283,
            "타입":"APT",
            "전용면적(m2)":94.7,
            "전용면적(평)":"28평",
            "법정동주소":"충청북도 청주시 서원구 개신동 446-2",
            "도로명주소":"충청북도 청주시 서원구 모충로12번길 4",
            "최고층":15.0,
            "최저층":15.0,
            "매매실거래가":16150.0,
            "전세실거래가":16000.0,
            "전세가율":"62~100%",
            "세대수":330.0,
            "난방방식":"개별난방",
            "방수":3,
            "욕실개수":2,
            "준공년월":"1992-02-21",
            "준공년차":30.0,
            "용적률":0,
            "건폐율":0,
            "최소공지가":86200000.0,
            "최대공지가":98800000.0,
            "y":36.624247,
            "x":127.465004
        },
        {
            "index":43,
            "아파트명":"시영(청주)",
            "코드":15431,
            "타입":"APT",
            "전용면적(m2)":47.77,
            "전용면적(평)":"14평",
            "법정동주소":"충청북도 청주시 서원구 개신동 506",
            "도로명주소":"충청북도 청주시 서원구 신율로 71",
            "최고층":6.0,
            "최저층":4.0,
            "매매실거래가":6900.0,
            "전세실거래가":5500.0,
            "전세가율":"69~96%",
            "세대수":141.0,
            "난방방식":"개별난방",
            "방수":2,
            "욕실개수":1,
            "준공년월":"1990-12-19",
            "준공년차":32.0,
            "용적률":116,
            "건폐율":55,
            "최소공지가":37500000.0,
            "최대공지가":41600000.0,
            "y":36.624399,
            "x":127.446901
        },
        {
            "index":188,
            "아파트명":"쌍용",
            "코드":100985,
            "타입":"APT",
            "전용면적(m2)":104.62,
            "전용면적(평)":"31평",
            "법정동주소":"충청북도 청주시 서원구 사직동 산 147-23",
            "도로명주소":"충청북도 청주시 서원구 호국로38번길 23",
            "최고층":8.0,
            "최저층":7.0,
            "매매실거래가":10500.0,
            "전세실거래가":13000.0,
            "전세가율":null,
            "세대수":180.0,
            "난방방식":"개별난방",
            "방수":3,
            "욕실개수":2,
            "준공년월":"1989-12-29",
            "준공년차":33.0,
            "용적률":0,
            "건폐율":0,
            "최소공지가":77600000.0,
            "최대공지가":82600000.0,
            "y":36.631707,
            "x":127.476782
        },
        {
            "index":136,
            "아파트명":"우성1차",
            "코드":12032,
            "타입":"APT",
            "전용면적(m2)":94.42,
            "전용면적(평)":"28평",
            "법정동주소":"충청북도 청주시 서원구 분평동 320",
            "도로명주소":"충청북도 청주시 서원구 1순환로1013번길 10",
            "최고층":15.0,
            "최저층":12.0,
            "매매실거래가":14900.0,
            "전세실거래가":12000.0,
            "전세가율":null,
            "세대수":412.0,
            "난방방식":"지역난방",
            "방수":3,
            "욕실개수":1,
            "준공년월":"1990-10-31",
            "준공년차":32.0,
            "용적률":0,
            "건폐율":0,
            "최소공지가":80700000.0,
            "최대공지가":91500000.0,
            "y":36.609545,
            "x":127.480531
        },
        {
            "index":139,
            "아파트명":"우성2차",
            "코드":7485,
            "타입":"APT",
            "전용면적(m2)":105.67,
            "전용면적(평)":"31평",
            "법정동주소":"충청북도 청주시 서원구 분평동 237",
            "도로명주소":"충청북도 청주시 서원구 청남로2005번길 45",
            "최고층":15.0,
            "최저층":10.0,
            "매매실거래가":14500.0,
            "전세실거래가":12600.0,
            "전세가율":null,
            "세대수":388.0,
            "난방방식":"지역난방",
            "방수":3,
            "욕실개수":2,
            "준공년월":"1990-11-30",
            "준공년차":32.0,
            "용적률":220,
            "건폐율":33,
            "최소공지가":95200000.0,
            "최대공지가":111000000.0,
            "y":36.610087,
            "x":127.482853
        },
        {
            "index":244,
            "아파트명":"유승한내들",
            "코드":25551,
            "타입":"APT",
            "전용면적(m2)":85.63,
            "전용면적(평)":"25평",
            "법정동주소":"충청북도 청주시 서원구 산남동 669",
            "도로명주소":"충청북도 청주시 서원구 두꺼비로 109",
            "최고층":15.0,
            "최저층":15.0,
            "매매실거래가":22900.0,
            "전세실거래가":21000.0,
            "전세가율":"76~102%",
            "세대수":464.0,
            "난방방식":"지역난방",
            "방수":3,
            "욕실개수":2,
            "준공년월":"2007-07-13",
            "준공년차":15.0,
            "용적률":207,
            "건폐율":18,
            "최소공지가":125000000.0,
            "최대공지가":149000000.0,
            "y":36.613903,
            "x":127.463476
        },
        {
            "index":105,
            "아파트명":"일신베네스트",
            "코드":102759,
            "타입":"APT",
            "전용면적(m2)":32.11,
            "전용면적(평)":"9평",
            "법정동주소":"충청북도 청주시 서원구 모충동 520-40",
            "도로명주소":"충청북도 청주시 서원구 모충로68번길 26",
            "최고층":11.0,
            "최저층":11.0,
            "매매실거래가":2600.0,
            "전세실거래가":null,
            "전세가율":null,
            "세대수":198.0,
            "난방방식":"개별난방",
            "방수":1,
            "욕실개수":1,
            "준공년월":"2004-11-03",
            "준공년차":18.0,
            "용적률":300,
            "건폐율":53,
            "최소공지가":22600000.0,
            "최대공지가":23300000.0,
            "y":36.626028,
            "x":127.47038
        },
        {
            "index":320,
            "아파트명":"주공",
            "코드":7407,
            "타입":"APT",
            "전용면적(m2)":49.56,
            "전용면적(평)":"14평",
            "법정동주소":"충청북도 청주시 서원구 수곡동 324",
            "도로명주소":"충청북도 청주시 서원구 구룡산로 319",
            "최고층":5.0,
            "최저층":5.0,
            "매매실거래가":13600.0,
            "전세실거래가":7000.0,
            "전세가율":"32~82%",
            "세대수":1240.0,
            "난방방식":"개별난방",
            "방수":2,
            "욕실개수":1,
            "준공년월":"1990-12-09",
            "준공년차":32.0,
            "용적률":0,
            "건폐율":0,
            "최소공지가":77400000.0,
            "최대공지가":88000000.0,
            "y":36.61938,
            "x":127.4797
        },
        {
            "index":108,
            "아파트명":"주공",
            "코드":7307,
            "타입":"APT",
            "전용면적(m2)":43.92,
            "전용면적(평)":"13평",
            "법정동주소":"충청북도 청주시 서원구 모충동 452",
            "도로명주소":"충청북도 청주시 서원구 쌍샘로 81",
            "최고층":5.0,
            "최저층":5.0,
            "매매실거래가":9000.0,
            "전세실거래가":6000.0,
            "전세가율":"66~109%",
            "세대수":330.0,
            "난방방식":"개별난방",
            "방수":2,
            "욕실개수":1,
            "준공년월":"1985-11-05",
            "준공년차":37.0,
            "용적률":0,
            "건폐율":0,
            "최소공지가":41900000.0,
            "최대공지가":47600000.0,
            "y":36.627138,
            "x":127.474756
        },
        {
            "index":110,
            "아파트명":"주공2단지",
            "코드":7309,
            "타입":"APT",
            "전용면적(m2)":49.48,
            "전용면적(평)":"14평",
            "법정동주소":"충청북도 청주시 서원구 모충동 516",
            "도로명주소":"충청북도 청주시 서원구 모충로 61",
            "최고층":5.0,
            "최저층":5.0,
            "매매실거래가":12300.0,
            "전세실거래가":8000.0,
            "전세가율":"59~74%",
            "세대수":640.0,
            "난방방식":"개별난방",
            "방수":2,
            "욕실개수":1,
            "준공년월":"1989-08-14",
            "준공년차":33.0,
            "용적률":0,
            "건폐율":0,
            "최소공지가":69800000.0,
            "최대공지가":75900000.0,
            "y":36.627622,
            "x":127.469956
        },
        {
            "index":142,
            "아파트명":"주공2단지",
            "코드":7487,
            "타입":"APT",
            "전용면적(m2)":57.84,
            "전용면적(평)":"17평",
            "법정동주소":"충청북도 청주시 서원구 분평동 1202",
            "도로명주소":"충청북도 청주시 서원구 1순환로1137번길 129",
            "최고층":20.0,
            "최저층":15.0,
            "매매실거래가":9850.0,
            "전세실거래가":7140.0,
            "전세가율":null,
            "세대수":1310.0,
            "난방방식":"지역난방",
            "방수":2,
            "욕실개수":1,
            "준공년월":"1997-06-18",
            "준공년차":25.0,
            "용적률":0,
            "건폐율":0,
            "최소공지가":50600000.0,
            "최대공지가":56700000.0,
            "y":36.612135,
            "x":127.491737
        },
        {
            "index":146,
            "아파트명":"주공3단지",
            "코드":7493,
            "타입":"APT",
            "전용면적(m2)":56.44,
            "전용면적(평)":"17평",
            "법정동주소":"충청북도 청주시 서원구 분평동 1200",
            "도로명주소":"충청북도 청주시 서원구 1순환로1137번길 130",
            "최고층":20.0,
            "최저층":15.0,
            "매매실거래가":9500.0,
            "전세실거래가":8500.0,
            "전세가율":"85~106%",
            "세대수":1330.0,
            "난방방식":"지역난방",
            "방수":2,
            "욕실개수":1,
            "준공년월":"1997-06-18",
            "준공년차":25.0,
            "용적률":0,
            "건폐율":0,
            "최소공지가":52300000.0,
            "최대공지가":58400000.0,
            "y":36.612569,
            "x":127.494239
        },
        {
            "index":152,
            "아파트명":"주공4단지",
            "코드":7498,
            "타입":"APT",
            "전용면적(m2)":56.26,
            "전용면적(평)":"17평",
            "법정동주소":"충청북도 청주시 서원구 분평동 1261",
            "도로명주소":"충청북도 청주시 서원구 1순환로1137번길 80",
            "최고층":20.0,
            "최저층":15.0,
            "매매실거래가":9500.0,
            "전세실거래가":8700.0,
            "전세가율":"55~107%",
            "세대수":1314.0,
            "난방방식":"지역난방",
            "방수":2,
            "욕실개수":1,
            "준공년월":"1999-06-26",
            "준공년차":23.0,
            "용적률":0,
            "건폐율":0,
            "최소공지가":52400000.0,
            "최대공지가":59100000.0,
            "y":36.60953,
            "x":127.49376
        },
        {
            "index":156,
            "아파트명":"주공5단지",
            "코드":7500,
            "타입":"APT",
            "전용면적(m2)":56.44,
            "전용면적(평)":"17평",
            "법정동주소":"충청북도 청주시 서원구 분평동 1360",
            "도로명주소":"충청북도 청주시 서원구 분평로 88-1",
            "최고층":15.0,
            "최저층":15.0,
            "매매실거래가":8600.0,
            "전세실거래가":9000.0,
            "전세가율":null,
            "세대수":1350.0,
            "난방방식":"지역난방",
            "방수":2,
            "욕실개수":1,
            "준공년월":"1998-02-13",
            "준공년차":24.0,
            "용적률":202,
            "건폐율":18,
            "최소공지가":51500000.0,
            "최대공지가":58900000.0,
            "y":36.607365,
            "x":127.495502
        },
        {
            "index":159,
            "아파트명":"주공6단지",
            "코드":7516,
            "타입":"APT",
            "전용면적(m2)":106.83,
            "전용면적(평)":"32평",
            "법정동주소":"충청북도 청주시 서원구 분평동 1366",
            "도로명주소":"충청북도 청주시 서원구 1순환로1137번길 19",
            "최고층":20.0,
            "최저층":15.0,
            "매매실거래가":19000.0,
            "전세실거래가":20000.0,
            "전세가율":"73~102%",
            "세대수":1120.0,
            "난방방식":"지역난방",
            "방수":3,
            "욕실개수":2,
            "준공년월":"1999-09-04",
            "준공년차":23.0,
            "용적률":221,
            "건폐율":19,
            "최소공지가":125000000.0,
            "최대공지가":159000000.0,
            "y":36.6074,
            "x":127.49186
        },
        {
            "index":162,
            "아파트명":"주공7단지",
            "코드":7510,
            "타입":"APT",
            "전용면적(m2)":103.84,
            "전용면적(평)":"31평",
            "법정동주소":"충청북도 청주시 서원구 분평동 1386",
            "도로명주소":"충청북도 청주시 서원구 분평로 18",
            "최고층":15.0,
            "최저층":15.0,
            "매매실거래가":14800.0,
            "전세실거래가":14000.0,
            "전세가율":null,
            "세대수":930.0,
            "난방방식":"지역난방",
            "방수":3,
            "욕실개수":2,
            "준공년월":"1997-12-06",
            "준공년차":25.0,
            "용적률":0,
            "건폐율":0,
            "최소공지가":122000000.0,
            "최대공지가":144000000.0,
            "y":36.607657,
            "x":127.487843
        },
        {
            "index":220,
            "아파트명":"주성",
            "코드":106607,
            "타입":"APT",
            "전용면적(m2)":60.69,
            "전용면적(평)":"18평",
            "법정동주소":"충청북도 청주시 서원구 사창동 285-12",
            "도로명주소":"충청북도 청주시 서원구 1순환로 689",
            "최고층":5.0,
            "최저층":5.0,
            "매매실거래가":null,
            "전세실거래가":null,
            "전세가율":null,
            "세대수":199.0,
            "난방방식":"개별난방",
            "방수":3,
            "욕실개수":1,
            "준공년월":"1981-06-01",
            "준공년차":41.0,
            "용적률":0,
            "건폐율":0,
            "최소공지가":null,
            "최대공지가":null,
            "y":36.632324,
            "x":127.461448
        },
        {
            "index":164,
            "아파트명":"주은프레지던트",
            "코드":11644,
            "타입":"APT",
            "전용면적(m2)":112.46,
            "전용면적(평)":"34평",
            "법정동주소":"충청북도 청주시 서원구 분평동 1255",
            "도로명주소":"충청북도 청주시 서원구 1순환로1137번길 79",
            "최고층":25.0,
            "최저층":15.0,
            "매매실거래가":25000.0,
            "전세실거래가":22050.0,
            "전세가율":"73~92%",
            "세대수":620.0,
            "난방방식":"지역난방",
            "방수":3,
            "욕실개수":2,
            "준공년월":"2001-11-19",
            "준공년차":21.0,
            "용적률":228,
            "건폐율":20,
            "최소공지가":144000000.0,
            "최대공지가":171000000.0,
            "y":36.61017,
            "x":127.491728
        },
        {
            "index":227,
            "아파트명":"중앙",
            "코드":12938,
            "타입":"APT",
            "전용면적(m2)":71.01,
            "전용면적(평)":"21평",
            "법정동주소":"충청북도 청주시 서원구 사창동 249-2",
            "도로명주소":"충청북도 청주시 서원구 천석로14번길 3",
            "최고층":5.0,
            "최저층":5.0,
            "매매실거래가":9200.0,
            "전세실거래가":7000.0,
            "전세가율":null,
            "세대수":80.0,
            "난방방식":"개별난방",
            "방수":3,
            "욕실개수":1,
            "준공년월":"1985-05-25",
            "준공년차":37.0,
            "용적률":352,
            "건폐율":72,
            "최소공지가":null,
            "최대공지가":null,
            "y":36.63712,
            "x":127.465876
        },
        {
            "index":330,
            "아파트명":"청주가경주공3단지",
            "코드":27617,
            "타입":"APT",
            "전용면적(m2)":67.68,
            "전용면적(평)":"20평",
            "법정동주소":"충청북도 청주시 서원구 죽림동 295",
            "도로명주소":"충청북도 청주시 서원구 대림로 493",
            "최고층":15.0,
            "최저층":13.0,
            "매매실거래가":17000.0,
            "전세실거래가":15000.0,
            "전세가율":"83~100%",
            "세대수":704.0,
            "난방방식":"지역난방",
            "방수":2,
            "욕실개수":1,
            "준공년월":"2003-11-17",
            "준공년차":19.0,
            "용적률":168,
            "건폐율":16,
            "최소공지가":null,
            "최대공지가":null,
            "y":36.614344,
            "x":127.443586
        },
        {
            "index":66,
            "아파트명":"청주가마힐데스하임",
            "코드":109416,
            "타입":"APT",
            "전용면적(m2)":104.52,
            "전용면적(평)":"31평",
            "법정동주소":"충청북도 청주시 서원구 남이면 가마리 378",
            "도로명주소":"충청북도 청주시 서원구 2순환로 1717",
            "최고층":25.0,
            "최저층":22.0,
            "매매실거래가":35000.0,
            "전세실거래가":23100.0,
            "전세가율":"68~76%",
            "세대수":988.0,
            "난방방식":"개별난방",
            "방수":3,
            "욕실개수":2,
            "준공년월":"2016-12-07",
            "준공년차":6.0,
            "용적률":199,
            "건폐율":13,
            "최소공지가":195000000.0,
            "최대공지가":216000000.0,
            "y":36.5983,
            "x":127.46962
        },
        {
            "index":44,
            "아파트명":"청주개신뜨란채2단지",
            "코드":17209,
            "타입":"APT",
            "전용면적(m2)":68.95,
            "전용면적(평)":"20평",
            "법정동주소":"충청북도 청주시 서원구 개신동 635",
            "도로명주소":"충청북도 청주시 서원구 경신로 68",
            "최고층":23.0,
            "최저층":15.0,
            "매매실거래가":14600.0,
            "전세실거래가":15800.0,
            "전세가율":"88~93%",
            "세대수":980.0,
            "난방방식":"지역난방",
            "방수":2,
            "욕실개수":1,
            "준공년월":"2000-12-11",
            "준공년차":22.0,
            "용적률":214,
            "건폐율":18,
            "최소공지가":92400000.0,
            "최대공지가":103000000.0,
            "y":36.620932,
            "x":127.449553
        },
        {
            "index":46,
            "아파트명":"청주개신주공1단지",
            "코드":25977,
            "타입":"APT",
            "전용면적(m2)":71.32,
            "전용면적(평)":"21평",
            "법정동주소":"충청북도 청주시 서원구 개신동 613",
            "도로명주소":"충청북도 청주시 서원구 경신로 67",
            "최고층":25.0,
            "최저층":8.0,
            "매매실거래가":13500.0,
            "전세실거래가":16000.0,
            "전세가율":"74~110%",
            "세대수":1398.0,
            "난방방식":"지역난방",
            "방수":2,
            "욕실개수":1,
            "준공년월":"2001-12-12",
            "준공년차":21.0,
            "용적률":204,
            "건폐율":18,
            "최소공지가":89700000.0,
            "최대공지가":103000000.0,
            "y":36.622985,
            "x":127.44898
        },
        {
            "index":52,
            "아파트명":"청주개신주공3단지",
            "코드":10630,
            "타입":"APT",
            "전용면적(m2)":97.29,
            "전용면적(평)":"29평",
            "법정동주소":"충청북도 청주시 서원구 개신동 590",
            "도로명주소":"충청북도 청주시 서원구 신율로 43",
            "최고층":20.0,
            "최저층":15.0,
            "매매실거래가":27700.0,
            "전세실거래가":26000.0,
            "전세가율":"77~92%",
            "세대수":634.0,
            "난방방식":"지역난방",
            "방수":3,
            "욕실개수":2,
            "준공년월":"2003-07-11",
            "준공년차":19.0,
            "용적률":166,
            "건폐율":11,
            "최소공지가":142000000.0,
            "최대공지가":167000000.0,
            "y":36.62231,
            "x":127.445295
        },
        {
            "index":56,
            "아파트명":"청주개신푸르지오",
            "코드":12983,
            "타입":"APT",
            "전용면적(m2)":107.65,
            "전용면적(평)":"32평",
            "법정동주소":"충청북도 청주시 서원구 개신동 634",
            "도로명주소":"충청북도 청주시 서원구 신율로 13",
            "최고층":25.0,
            "최저층":18.0,
            "매매실거래가":33000.0,
            "전세실거래가":24500.0,
            "전세가율":null,
            "세대수":920.0,
            "난방방식":"지역난방",
            "방수":3,
            "욕실개수":2,
            "준공년월":"2004-11-26",
            "준공년차":18.0,
            "용적률":242,
            "건폐율":14,
            "최소공지가":197000000.0,
            "최대공지가":235000000.0,
            "y":36.619246,
            "x":127.447307
        },
        {
            "index":167,
            "아파트명":"청주분평뜨란채1단지",
            "코드":23894,
            "타입":"APT",
            "전용면적(m2)":68.23,
            "전용면적(평)":"20평",
            "법정동주소":"충청북도 청주시 서원구 분평동 1211",
            "도로명주소":"충청북도 청주시 서원구 월평로 25",
            "최고층":20.0,
            "최저층":14.0,
            "매매실거래가":13000.0,
            "전세실거래가":11500.0,
            "전세가율":null,
            "세대수":982.0,
            "난방방식":"지역난방",
            "방수":2,
            "욕실개수":1,
            "준공년월":"2000-10-06",
            "준공년차":22.0,
            "용적률":215,
            "건폐율":16,
            "최소공지가":null,
            "최대공지가":null,
            "y":36.612002,
            "x":127.488061
        },
        {
            "index":245,
            "아파트명":"청주산남푸르지오",
            "코드":25919,
            "타입":"APT",
            "전용면적(m2)":96.05,
            "전용면적(평)":"29평",
            "법정동주소":"충청북도 청주시 서원구 산남동 679",
            "도로명주소":"충청북도 청주시 서원구 두꺼비로 53",
            "최고층":15.0,
            "최저층":13.0,
            "매매실거래가":31000.0,
            "전세실거래가":21000.0,
            "전세가율":"73~90%",
            "세대수":760.0,
            "난방방식":"지역난방",
            "방수":3,
            "욕실개수":2,
            "준공년월":"2007-04-24",
            "준공년차":15.0,
            "용적률":179,
            "건폐율":16,
            "최소공지가":171000000.0,
            "최대공지가":198000000.0,
            "y":36.609153,
            "x":127.463308
        },
        {
            "index":261,
            "아파트명":"청주성화2다안채6단지",
            "코드":103529,
            "타입":"APT",
            "전용면적(m2)":110.97,
            "전용면적(평)":"33평",
            "법정동주소":"충청북도 청주시 서원구 성화동 1034",
            "도로명주소":"충청북도 청주시 서원구 구룡산로52번길 51",
            "최고층":15.0,
            "최저층":12.0,
            "매매실거래가":null,
            "전세실거래가":null,
            "전세가율":"83~91%",
            "세대수":533.0,
            "난방방식":"지역난방",
            "방수":3,
            "욕실개수":2,
            "준공년월":"2013-02-08",
            "준공년차":9.0,
            "용적률":146,
            "건폐율":15,
            "최소공지가":201000000.0,
            "최대공지가":232000000.0,
            "y":36.611839,
            "x":127.451451
        },
        {
            "index":248,
            "아파트명":"청주현진에버빌",
            "코드":25550,
            "타입":"APT",
            "전용면적(m2)":110.42,
            "전용면적(평)":"33평",
            "법정동주소":"충청북도 청주시 서원구 산남동 1103",
            "도로명주소":"충청북도 청주시 서원구 탑골로 6",
            "최고층":15.0,
            "최저층":10.0,
            "매매실거래가":29900.0,
            "전세실거래가":30000.0,
            "전세가율":"76~100%",
            "세대수":477.0,
            "난방방식":"지역난방",
            "방수":3,
            "욕실개수":2,
            "준공년월":"2006-12-15",
            "준공년차":16.0,
            "용적률":190,
            "건폐율":18,
            "최소공지가":197000000.0,
            "최대공지가":226000000.0,
            "y":36.611216,
            "x":127.473142
        },
        {
            "index":60,
            "아파트명":"태암베스트윙",
            "코드":25720,
            "타입":"APT",
            "전용면적(m2)":112.48,
            "전용면적(평)":"34평",
            "법정동주소":"충청북도 청주시 서원구 개신동 8",
            "도로명주소":"충청북도 청주시 서원구 1순환로751번길 29",
            "최고층":15.0,
            "최저층":8.0,
            "매매실거래가":22500.0,
            "전세실거래가":20000.0,
            "전세가율":null,
            "세대수":118.0,
            "난방방식":"개별난방",
            "방수":3,
            "욕실개수":2,
            "준공년월":"2005-09-05",
            "준공년차":17.0,
            "용적률":175,
            "건폐율":21,
            "최소공지가":129000000.0,
            "최대공지가":145000000.0,
            "y":36.62737,
            "x":127.46474
        },
        {
            "index":191,
            "아파트명":"평화",
            "코드":15466,
            "타입":"APT",
            "전용면적(m2)":88.54,
            "전용면적(평)":"26평",
            "법정동주소":"충청북도 청주시 서원구 사직동 238-45",
            "도로명주소":"충청북도 청주시 서원구 직지대로772번길 14",
            "최고층":5.0,
            "최저층":5.0,
            "매매실거래가":11401.0,
            "전세실거래가":9000.0,
            "전세가율":null,
            "세대수":130.0,
            "난방방식":"개별난방",
            "방수":3,
            "욕실개수":1,
            "준공년월":"1985-11-15",
            "준공년차":37.0,
            "용적률":0,
            "건폐율":0,
            "최소공지가":63200000.0,
            "최대공지가":68300000.0,
            "y":36.643949,
            "x":127.477426
        },
        {
            "index":193,
            "아파트명":"푸르지오캐슬1,2,3단지",
            "코드":26944,
            "타입":"APT",
            "전용면적(m2)":83.14,
            "전용면적(평)":"25평",
            "법정동주소":"충청북도 청주시 서원구 사직동 931",
            "도로명주소":"충청북도 청주시 서원구 예체로 68",
            "최고층":25.0,
            "최저층":10.0,
            "매매실거래가":25350.0,
            "전세실거래가":23700.0,
            "전세가율":"89~100%",
            "세대수":1832.0,
            "난방방식":"지역난방",
            "방수":3,
            "욕실개수":2,
            "준공년월":"2010-11-19",
            "준공년차":12.0,
            "용적률":249,
            "건폐율":0,
            "최소공지가":null,
            "최대공지가":null,
            "y":36.632331,
            "x":127.47035
        },
        {
            "index":200,
            "아파트명":"푸르지오캐슬4단지",
            "코드":106824,
            "타입":"APT",
            "전용면적(m2)":110.43,
            "전용면적(평)":"33평",
            "법정동주소":"충청북도 청주시 서원구 사직동 937",
            "도로명주소":"충청북도 청주시 서원구 창직로 50",
            "최고층":25.0,
            "최저층":15.0,
            "매매실거래가":36000.0,
            "전세실거래가":26000.0,
            "전세가율":"65~91%",
            "세대수":1219.0,
            "난방방식":"지역난방",
            "방수":3,
            "욕실개수":2,
            "준공년월":"2010-11-19",
            "준공년차":12.0,
            "용적률":254,
            "건폐율":16,
            "최소공지가":190000000.0,
            "최대공지가":234000000.0,
            "y":36.629935,
            "x":127.467368
        },
        {
            "index":204,
            "아파트명":"푸르지오캐슬5단지",
            "코드":106825,
            "타입":"APT",
            "전용면적(m2)":94.84,
            "전용면적(평)":"28평",
            "법정동주소":"충청북도 청주시 서원구 사직동 934",
            "도로명주소":"충청북도 청주시 서원구 예체로 30",
            "최고층":25.0,
            "최저층":18.0,
            "매매실거래가":26900.0,
            "전세실거래가":26000.0,
            "전세가율":"83~93%",
            "세대수":548.0,
            "난방방식":"지역난방",
            "방수":3,
            "욕실개수":2,
            "준공년월":"2010-11-19",
            "준공년차":12.0,
            "용적률":245,
            "건폐율":14,
            "최소공지가":158000000.0,
            "최대공지가":187000000.0,
            "y":36.630269,
            "x":127.469502
        },
        {
            "index":324,
            "아파트명":"한마음1차",
            "코드":12786,
            "타입":"APT",
            "전용면적(m2)":75.63,
            "전용면적(평)":"22평",
            "법정동주소":"충청북도 청주시 서원구 수곡동 777",
            "도로명주소":"충청북도 청주시 서원구 수곡로 78",
            "최고층":15.0,
            "최저층":15.0,
            "매매실거래가":15000.0,
            "전세실거래가":14000.0,
            "전세가율":"82~97%",
            "세대수":435.0,
            "난방방식":"중앙난방",
            "방수":3,
            "욕실개수":1,
            "준공년월":"1995-04-27",
            "준공년차":27.0,
            "용적률":0,
            "건폐율":0,
            "최소공지가":76400000.0,
            "최대공지가":88100000.0,
            "y":36.61892,
            "x":127.47244
        },
        {
            "index":325,
            "아파트명":"한마음2차",
            "코드":12787,
            "타입":"APT",
            "전용면적(m2)":130.09,
            "전용면적(평)":"39평",
            "법정동주소":"충청북도 청주시 서원구 수곡동 775",
            "도로명주소":"충청북도 청주시 서원구 수곡로 100",
            "최고층":13.0,
            "최저층":12.0,
            "매매실거래가":21700.0,
            "전세실거래가":22000.0,
            "전세가율":"88~100%",
            "세대수":228.0,
            "난방방식":"지역난방",
            "방수":3,
            "욕실개수":2,
            "준공년월":"1995-04-24",
            "준공년차":27.0,
            "용적률":0,
            "건폐율":0,
            "최소공지가":110000000.0,
            "최대공지가":133000000.0,
            "y":36.620599,
            "x":127.471536
        },
        {
            "index":61,
            "아파트명":"한진신세대",
            "코드":15432,
            "타입":"APT",
            "전용면적(m2)":42.79,
            "전용면적(평)":"12평",
            "법정동주소":"충청북도 청주시 서원구 개신동 41-5",
            "도로명주소":"충청북도 청주시 서원구 모충로3번길 81",
            "최고층":15.0,
            "최저층":15.0,
            "매매실거래가":4950.0,
            "전세실거래가":4500.0,
            "전세가율":null,
            "세대수":336.0,
            "난방방식":"개별난방",
            "방수":1,
            "욕실개수":1,
            "준공년월":"1996-02-14",
            "준공년차":26.0,
            "용적률":393,
            "건폐율":48,
            "최소공지가":31100000.0,
            "최대공지가":35200000.0,
            "y":36.628185,
            "x":127.462953
        },
        {
            "index":114,
            "아파트명":"한화포레나청주매봉",
            "코드":148319,
            "타입":"ABYG",
            "전용면적(m2)":99.39,
            "전용면적(평)":"30평",
            "법정동주소":"충청북도 청주시 서원구 모충동 산 62-10번지 일원",
            "도로명주소":"충청북도 청주시 서원구",
            "최고층":29.0,
            "최저층":8.0,
            "매매실거래가":null,
            "전세실거래가":null,
            "전세가율":null,
            "세대수":1849.0,
            "난방방식":"개별난방",
            "방수":3,
            "욕실개수":2,
            "준공년월":"2025-09-01",
            "준공년차":-3.0,
            "용적률":213,
            "건폐율":16,
            "최소공지가":null,
            "최대공지가":null,
            "y":36.622243,
            "x":127.478121
        },
        {
            "index":62,
            "아파트명":"현대",
            "코드":7288,
            "타입":"APT",
            "전용면적(m2)":87.87,
            "전용면적(평)":"26평",
            "법정동주소":"충청북도 청주시 서원구 개신동 278-10",
            "도로명주소":"충청북도 청주시 서원구 성봉로220번길 23",
            "최고층":15.0,
            "최저층":9.0,
            "매매실거래가":14000.0,
            "전세실거래가":13125.0,
            "전세가율":"73~107%",
            "세대수":511.0,
            "난방방식":"지역난방",
            "방수":3,
            "욕실개수":2,
            "준공년월":"1990-12-11",
            "준공년차":32.0,
            "용적률":0,
            "건폐율":0,
            "최소공지가":83000000.0,
            "최대공지가":95900000.0,
            "y":36.624916,
            "x":127.45156
        },
        {
            "index":228,
            "아파트명":"현대(227-2)",
            "코드":7390,
            "타입":"APT",
            "전용면적(m2)":89.48,
            "전용면적(평)":"27평",
            "법정동주소":"충청북도 청주시 서원구 사창동 227-2",
            "도로명주소":"충청북도 청주시 서원구 사직대로157번길 18",
            "최고층":14.0,
            "최저층":7.0,
            "매매실거래가":14500.0,
            "전세실거래가":12000.0,
            "전세가율":null,
            "세대수":229.0,
            "난방방식":"중앙난방",
            "방수":3,
            "욕실개수":1,
            "준공년월":"1988-12-06",
            "준공년차":34.0,
            "용적률":0,
            "건폐율":0,
            "최소공지가":86400000.0,
            "최대공지가":96800000.0,
            "y":36.636295,
            "x":127.464708
        },
        {
            "index":175,
            "아파트명":"현대대우",
            "코드":7511,
            "타입":"APT",
            "전용면적(m2)":104.14,
            "전용면적(평)":"31평",
            "법정동주소":"충청북도 청주시 서원구 분평동 1249",
            "도로명주소":"충청북도 청주시 서원구 월평로 24",
            "최고층":25.0,
            "최저층":18.0,
            "매매실거래가":28800.0,
            "전세실거래가":23000.0,
            "전세가율":"88~96%",
            "세대수":1179.0,
            "난방방식":"지역난방",
            "방수":3,
            "욕실개수":2,
            "준공년월":"1999-07-23",
            "준공년차":23.0,
            "용적률":242,
            "건폐율":16,
            "최소공지가":143000000.0,
            "최대공지가":176000000.0,
            "y":36.60979,
            "x":127.487181
        },
        {
            "index":119,
            "아파트명":"형석",
            "코드":7313,
            "타입":"APT",
            "전용면적(m2)":47.6,
            "전용면적(평)":"14평",
            "법정동주소":"충청북도 청주시 서원구 모충동 251-1",
            "도로명주소":"충청북도 청주시 서원구 남들로35번길 61",
            "최고층":5.0,
            "최저층":5.0,
            "매매실거래가":9000.0,
            "전세실거래가":5000.0,
            "전세가율":null,
            "세대수":204.0,
            "난방방식":"개별난방",
            "방수":2,
            "욕실개수":1,
            "준공년월":"1983-08-03",
            "준공년차":39.0,
            "용적률":0,
            "건폐율":0,
            "최소공지가":37500000.0,
            "최대공지가":42800000.0,
            "y":36.621379,
            "x":127.480877
        }
    ]
}