{
    "schema":{
        "fields":[
            {
                "name":"index",
                "type":"integer"
            },
            {
                "name":"sort",
                "type":"string"
            },
            {
                "name":"name",
                "type":"string"
            },
            {
                "name":"search_code",
                "type":"integer"
            },
            {
                "name":"apt_type",
                "type":"string"
            },
            {
                "name":"apt_year",
                "type":"number"
            },
            {
                "name":"value_score",
                "type":"number"
            },
            {
                "name":"region",
                "type":"string"
            },
            {
                "name":"region_code",
                "type":"string"
            },
            {
                "name":"sub_region_code",
                "type":"string"
            }
        ],
        "primaryKey":[
            "index"
        ],
        "pandas_version":"1.4.0"
    },
    "data":[
        {
            "index":0,
            "sort":"balanced",
            "name":"칸타빌더테라스2단지",
            "search_code":117349,
            "apt_type":"아파트",
            "apt_year":3.0,
            "value_score":60.514,
            "region":"충청북도 청주시 상당구",
            "region_code":"Chungcheongbukdo",
            "sub_region_code":"4311100000_Chungcheongbukdo_Cheongju_Sangdang"
        },
        {
            "index":1,
            "sort":"balanced",
            "name":"동남지구우미린풀하우스",
            "search_code":121996,
            "apt_type":"아파트",
            "apt_year":2.0,
            "value_score":60.172,
            "region":"충청북도 청주시 상당구",
            "region_code":"Chungcheongbukdo",
            "sub_region_code":"4311100000_Chungcheongbukdo_Cheongju_Sangdang"
        },
        {
            "index":2,
            "sort":"balanced",
            "name":"호반써밋브룩사이드",
            "search_code":140150,
            "apt_type":"분양권",
            "apt_year":-1.0,
            "value_score":60.1705,
            "region":"충청북도 청주시 상당구",
            "region_code":"Chungcheongbukdo",
            "sub_region_code":"4311100000_Chungcheongbukdo_Cheongju_Sangdang"
        },
        {
            "index":3,
            "sort":"balanced",
            "name":"청주동남시티프라디움B1블록",
            "search_code":119336,
            "apt_type":"아파트",
            "apt_year":2.0,
            "value_score":60.127,
            "region":"충청북도 청주시 상당구",
            "region_code":"Chungcheongbukdo",
            "sub_region_code":"4311100000_Chungcheongbukdo_Cheongju_Sangdang"
        },
        {
            "index":4,
            "sort":"balanced",
            "name":"청주센트럴자이",
            "search_code":111666,
            "apt_type":"아파트",
            "apt_year":4.0,
            "value_score":59.7255,
            "region":"충청북도 청주시 상당구",
            "region_code":"Chungcheongbukdo",
            "sub_region_code":"4311100000_Chungcheongbukdo_Cheongju_Sangdang"
        },
        {
            "index":5,
            "sort":"balanced",
            "name":"중흥S-클래스더퍼스트",
            "search_code":111567,
            "apt_type":"아파트",
            "apt_year":4.0,
            "value_score":59.3255,
            "region":"충청북도 청주시 상당구",
            "region_code":"Chungcheongbukdo",
            "sub_region_code":"4311100000_Chungcheongbukdo_Cheongju_Sangdang"
        },
        {
            "index":6,
            "sort":"balanced",
            "name":"문화센트럴칸타빌",
            "search_code":111702,
            "apt_type":"아파트",
            "apt_year":4.0,
            "value_score":58.791,
            "region":"충청북도 청주시 상당구",
            "region_code":"Chungcheongbukdo",
            "sub_region_code":"4311100000_Chungcheongbukdo_Cheongju_Sangdang"
        },
        {
            "index":7,
            "sort":"balanced",
            "name":"청주용정한라비발디2단지",
            "search_code":102705,
            "apt_type":"아파트",
            "apt_year":9.0,
            "value_score":58.542,
            "region":"충청북도 청주시 상당구",
            "region_code":"Chungcheongbukdo",
            "sub_region_code":"4311100000_Chungcheongbukdo_Cheongju_Sangdang"
        },
        {
            "index":8,
            "sort":"balanced",
            "name":"청주동남지구우미린에듀포레",
            "search_code":126163,
            "apt_type":"아파트",
            "apt_year":0.0,
            "value_score":58.267,
            "region":"충청북도 청주시 상당구",
            "region_code":"Chungcheongbukdo",
            "sub_region_code":"4311100000_Chungcheongbukdo_Cheongju_Sangdang"
        },
        {
            "index":9,
            "sort":"balanced",
            "name":"청주동남시티프라디움B2블록",
            "search_code":119337,
            "apt_type":"아파트",
            "apt_year":2.0,
            "value_score":58.027,
            "region":"충청북도 청주시 상당구",
            "region_code":"Chungcheongbukdo",
            "sub_region_code":"4311100000_Chungcheongbukdo_Cheongju_Sangdang"
        },
        {
            "index":10,
            "sort":"living",
            "name":"동남지구우미린풀하우스",
            "search_code":121996,
            "apt_type":"아파트",
            "apt_year":2.0,
            "value_score":68.347,
            "region":"충청북도 청주시 상당구",
            "region_code":"Chungcheongbukdo",
            "sub_region_code":"4311100000_Chungcheongbukdo_Cheongju_Sangdang"
        },
        {
            "index":11,
            "sort":"living",
            "name":"호반써밋브룩사이드",
            "search_code":140150,
            "apt_type":"분양권",
            "apt_year":-1.0,
            "value_score":68.3455,
            "region":"충청북도 청주시 상당구",
            "region_code":"Chungcheongbukdo",
            "sub_region_code":"4311100000_Chungcheongbukdo_Cheongju_Sangdang"
        },
        {
            "index":12,
            "sort":"living",
            "name":"칸타빌더테라스2단지",
            "search_code":117349,
            "apt_type":"아파트",
            "apt_year":3.0,
            "value_score":67.414,
            "region":"충청북도 청주시 상당구",
            "region_code":"Chungcheongbukdo",
            "sub_region_code":"4311100000_Chungcheongbukdo_Cheongju_Sangdang"
        },
        {
            "index":13,
            "sort":"living",
            "name":"청주센트럴자이",
            "search_code":111666,
            "apt_type":"아파트",
            "apt_year":4.0,
            "value_score":67.3755,
            "region":"충청북도 청주시 상당구",
            "region_code":"Chungcheongbukdo",
            "sub_region_code":"4311100000_Chungcheongbukdo_Cheongju_Sangdang"
        },
        {
            "index":14,
            "sort":"living",
            "name":"중흥S-클래스더퍼스트",
            "search_code":111567,
            "apt_type":"아파트",
            "apt_year":4.0,
            "value_score":67.1255,
            "region":"충청북도 청주시 상당구",
            "region_code":"Chungcheongbukdo",
            "sub_region_code":"4311100000_Chungcheongbukdo_Cheongju_Sangdang"
        },
        {
            "index":15,
            "sort":"living",
            "name":"청주동남시티프라디움B1블록",
            "search_code":119336,
            "apt_type":"아파트",
            "apt_year":2.0,
            "value_score":66.442,
            "region":"충청북도 청주시 상당구",
            "region_code":"Chungcheongbukdo",
            "sub_region_code":"4311100000_Chungcheongbukdo_Cheongju_Sangdang"
        },
        {
            "index":16,
            "sort":"living",
            "name":"청주용정한라비발디2단지",
            "search_code":102705,
            "apt_type":"아파트",
            "apt_year":9.0,
            "value_score":65.592,
            "region":"충청북도 청주시 상당구",
            "region_code":"Chungcheongbukdo",
            "sub_region_code":"4311100000_Chungcheongbukdo_Cheongju_Sangdang"
        },
        {
            "index":17,
            "sort":"living",
            "name":"우미린에듀파크2단지",
            "search_code":110558,
            "apt_type":"아파트",
            "apt_year":4.0,
            "value_score":64.37,
            "region":"충청북도 청주시 상당구",
            "region_code":"Chungcheongbukdo",
            "sub_region_code":"4311100000_Chungcheongbukdo_Cheongju_Sangdang"
        },
        {
            "index":18,
            "sort":"living",
            "name":"청주동남지구우미린에듀포레",
            "search_code":126163,
            "apt_type":"아파트",
            "apt_year":0.0,
            "value_score":63.592,
            "region":"충청북도 청주시 상당구",
            "region_code":"Chungcheongbukdo",
            "sub_region_code":"4311100000_Chungcheongbukdo_Cheongju_Sangdang"
        },
        {
            "index":19,
            "sort":"living",
            "name":"탑동힐데스하임",
            "search_code":129973,
            "apt_type":"분양권",
            "apt_year":0.0,
            "value_score":63.466,
            "region":"충청북도 청주시 상당구",
            "region_code":"Chungcheongbukdo",
            "sub_region_code":"4311100000_Chungcheongbukdo_Cheongju_Sangdang"
        },
        {
            "index":20,
            "sort":"infra",
            "name":"문화센트럴칸타빌",
            "search_code":111702,
            "apt_type":"아파트",
            "apt_year":4.0,
            "value_score":55.5623157895,
            "region":"충청북도 청주시 상당구",
            "region_code":"Chungcheongbukdo",
            "sub_region_code":"4311100000_Chungcheongbukdo_Cheongju_Sangdang"
        },
        {
            "index":21,
            "sort":"infra",
            "name":"청주동남시티프라디움B1블록",
            "search_code":119336,
            "apt_type":"아파트",
            "apt_year":2.0,
            "value_score":53.3530526316,
            "region":"충청북도 청주시 상당구",
            "region_code":"Chungcheongbukdo",
            "sub_region_code":"4311100000_Chungcheongbukdo_Cheongju_Sangdang"
        },
        {
            "index":22,
            "sort":"infra",
            "name":"청주동남지구우미린에듀포레",
            "search_code":126163,
            "apt_type":"아파트",
            "apt_year":0.0,
            "value_score":52.7214736842,
            "region":"충청북도 청주시 상당구",
            "region_code":"Chungcheongbukdo",
            "sub_region_code":"4311100000_Chungcheongbukdo_Cheongju_Sangdang"
        },
        {
            "index":23,
            "sort":"infra",
            "name":"칸타빌더테라스2단지",
            "search_code":117349,
            "apt_type":"아파트",
            "apt_year":3.0,
            "value_score":52.5755789474,
            "region":"충청북도 청주시 상당구",
            "region_code":"Chungcheongbukdo",
            "sub_region_code":"4311100000_Chungcheongbukdo_Cheongju_Sangdang"
        },
        {
            "index":24,
            "sort":"infra",
            "name":"청주동남시티프라디움B2블록",
            "search_code":119337,
            "apt_type":"아파트",
            "apt_year":2.0,
            "value_score":52.4056842105,
            "region":"충청북도 청주시 상당구",
            "region_code":"Chungcheongbukdo",
            "sub_region_code":"4311100000_Chungcheongbukdo_Cheongju_Sangdang"
        },
        {
            "index":25,
            "sort":"infra",
            "name":"건영",
            "search_code":7036,
            "apt_type":"아파트",
            "apt_year":23.0,
            "value_score":52.1101052632,
            "region":"충청북도 청주시 상당구",
            "region_code":"Chungcheongbukdo",
            "sub_region_code":"4311100000_Chungcheongbukdo_Cheongju_Sangdang"
        },
        {
            "index":26,
            "sort":"infra",
            "name":"청주센트럴자이",
            "search_code":111666,
            "apt_type":"아파트",
            "apt_year":4.0,
            "value_score":51.4743157895,
            "region":"충청북도 청주시 상당구",
            "region_code":"Chungcheongbukdo",
            "sub_region_code":"4311100000_Chungcheongbukdo_Cheongju_Sangdang"
        },
        {
            "index":27,
            "sort":"infra",
            "name":"청주행정타운코아루휴티스",
            "search_code":116747,
            "apt_type":"아파트",
            "apt_year":2.0,
            "value_score":51.2703157895,
            "region":"충청북도 청주시 상당구",
            "region_code":"Chungcheongbukdo",
            "sub_region_code":"4311100000_Chungcheongbukdo_Cheongju_Sangdang"
        },
        {
            "index":28,
            "sort":"infra",
            "name":"청주용정한라비발디2단지",
            "search_code":102705,
            "apt_type":"아파트",
            "apt_year":9.0,
            "value_score":51.1162105263,
            "region":"충청북도 청주시 상당구",
            "region_code":"Chungcheongbukdo",
            "sub_region_code":"4311100000_Chungcheongbukdo_Cheongju_Sangdang"
        },
        {
            "index":29,
            "sort":"infra",
            "name":"동남지구우미린풀하우스",
            "search_code":121996,
            "apt_type":"아파트",
            "apt_year":2.0,
            "value_score":51.0435789474,
            "region":"충청북도 청주시 상당구",
            "region_code":"Chungcheongbukdo",
            "sub_region_code":"4311100000_Chungcheongbukdo_Cheongju_Sangdang"
        },
        {
            "index":30,
            "sort":"education",
            "name":"청주동남시티프라디움B1블록",
            "search_code":119336,
            "apt_type":"아파트",
            "apt_year":2.0,
            "value_score":60.909,
            "region":"충청북도 청주시 상당구",
            "region_code":"Chungcheongbukdo",
            "sub_region_code":"4311100000_Chungcheongbukdo_Cheongju_Sangdang"
        },
        {
            "index":31,
            "sort":"education",
            "name":"청주센트럴자이",
            "search_code":111666,
            "apt_type":"아파트",
            "apt_year":4.0,
            "value_score":60.501,
            "region":"충청북도 청주시 상당구",
            "region_code":"Chungcheongbukdo",
            "sub_region_code":"4311100000_Chungcheongbukdo_Cheongju_Sangdang"
        },
        {
            "index":32,
            "sort":"education",
            "name":"중흥S-클래스더퍼스트",
            "search_code":111567,
            "apt_type":"아파트",
            "apt_year":4.0,
            "value_score":60.251,
            "region":"충청북도 청주시 상당구",
            "region_code":"Chungcheongbukdo",
            "sub_region_code":"4311100000_Chungcheongbukdo_Cheongju_Sangdang"
        },
        {
            "index":33,
            "sort":"education",
            "name":"청주용정한라비발디2단지",
            "search_code":102705,
            "apt_type":"아파트",
            "apt_year":9.0,
            "value_score":59.934,
            "region":"충청북도 청주시 상당구",
            "region_code":"Chungcheongbukdo",
            "sub_region_code":"4311100000_Chungcheongbukdo_Cheongju_Sangdang"
        },
        {
            "index":34,
            "sort":"education",
            "name":"동남지구우미린풀하우스",
            "search_code":121996,
            "apt_type":"아파트",
            "apt_year":2.0,
            "value_score":59.819,
            "region":"충청북도 청주시 상당구",
            "region_code":"Chungcheongbukdo",
            "sub_region_code":"4311100000_Chungcheongbukdo_Cheongju_Sangdang"
        },
        {
            "index":35,
            "sort":"education",
            "name":"호반써밋브룩사이드",
            "search_code":140150,
            "apt_type":"분양권",
            "apt_year":-1.0,
            "value_score":59.816,
            "region":"충청북도 청주시 상당구",
            "region_code":"Chungcheongbukdo",
            "sub_region_code":"4311100000_Chungcheongbukdo_Cheongju_Sangdang"
        },
        {
            "index":36,
            "sort":"education",
            "name":"청주동남지구우미린에듀포레",
            "search_code":126163,
            "apt_type":"아파트",
            "apt_year":0.0,
            "value_score":59.559,
            "region":"충청북도 청주시 상당구",
            "region_code":"Chungcheongbukdo",
            "sub_region_code":"4311100000_Chungcheongbukdo_Cheongju_Sangdang"
        },
        {
            "index":37,
            "sort":"education",
            "name":"청주동남시티프라디움B2블록",
            "search_code":119337,
            "apt_type":"아파트",
            "apt_year":2.0,
            "value_score":59.409,
            "region":"충청북도 청주시 상당구",
            "region_code":"Chungcheongbukdo",
            "sub_region_code":"4311100000_Chungcheongbukdo_Cheongju_Sangdang"
        },
        {
            "index":38,
            "sort":"education",
            "name":"칸타빌더테라스2단지",
            "search_code":117349,
            "apt_type":"아파트",
            "apt_year":3.0,
            "value_score":59.328,
            "region":"충청북도 청주시 상당구",
            "region_code":"Chungcheongbukdo",
            "sub_region_code":"4311100000_Chungcheongbukdo_Cheongju_Sangdang"
        },
        {
            "index":39,
            "sort":"education",
            "name":"문화센트럴칸타빌",
            "search_code":111702,
            "apt_type":"아파트",
            "apt_year":4.0,
            "value_score":58.807,
            "region":"충청북도 청주시 상당구",
            "region_code":"Chungcheongbukdo",
            "sub_region_code":"4311100000_Chungcheongbukdo_Cheongju_Sangdang"
        }
    ]
}